{
  "chunks": [
    {
      "chunk_id": "docs.README#chunk-001",
      "end_line": 4,
      "heading": "文档目录",
      "keywords": [
        "docs",
        "md",
        "readme",
        "文档目录",
        "中存放项",
        "于集中存",
        "作规范等",
        "协作规范",
        "和协作规",
        "存放项目",
        "工程标准",
        "录用于集",
        "录结构和",
        "放项目架",
        "本目录用",
        "构和协作",
        "用于集中",
        "目录用于",
        "目录结构",
        "结构和协"
      ],
      "relations": {
        "capabilities": [
          "docs"
        ],
        "framework": null,
        "kind": "readme",
        "language": "docs",
        "service": null
      },
      "source_path": "docs/README.md",
      "start_line": 1,
      "summary": "文档目录 in docs/README.md"
    },
    {
      "chunk_id": "docs.README#chunk-002",
      "end_line": 9,
      "heading": "索引",
      "keywords": [
        "docs",
        "md",
        "readme",
        "standards",
        "superpowers",
        "公司正式",
        "决策和参",
        "包含规则",
        "协作流程",
        "参考资料",
        "司正式规",
        "和参考资",
        "工程规范",
        "式规范资",
        "正式规范",
        "流程",
        "策和参考",
        "索引",
        "规范资产",
        "计与计划"
      ],
      "relations": {
        "capabilities": [
          "docs"
        ],
        "framework": null,
        "kind": "readme",
        "language": "docs",
        "service": null
      },
      "source_path": "docs/README.md",
      "start_line": 5,
      "summary": "索引 in docs/README.md"
    },
    {
      "chunk_id": "docs.README#chunk-003",
      "end_line": 12,
      "heading": "维护约定",
      "keywords": [
        "docs",
        "md",
        "readme",
        "维护约定",
        "brief",
        "check",
        "format",
        "generate",
        "markdown",
        "memory",
        "python",
        "standards",
        "tools",
        "公司治理",
        "司治理资",
        "和公司治",
        "文和公司",
        "正文和公",
        "治理资料",
        "理资料统"
      ],
      "relations": {
        "capabilities": [
          "docs"
        ],
        "framework": null,
        "kind": "readme",
        "language": "docs",
        "service": null
      },
      "source_path": "docs/README.md",
      "start_line": 10,
      "summary": "维护约定 in docs/README.md"
    },
    {
      "chunk_id": "docs.standards.README#chunk-001",
      "end_line": 4,
      "heading": "工程规范目录",
      "keywords": [
        "docs",
        "md",
        "readme",
        "standards",
        "工程规范目录",
        "业务无关",
        "于存放业",
        "务无关的",
        "存放业务",
        "工程规范",
        "录是项目",
        "放业务无",
        "是项目工",
        "本目录是",
        "用于存放",
        "的统一入",
        "目工程规",
        "目录是项",
        "程规范的",
        "程规范目"
      ],
      "relations": {
        "capabilities": [
          "docs",
          "standards"
        ],
        "framework": null,
        "kind": "readme",
        "language": "docs",
        "service": null
      },
      "source_path": "docs/standards/README.md",
      "start_line": 1,
      "summary": "工程规范目录 in docs/standards/README.md"
    },
    {
      "chunk_id": "docs.standards.README#chunk-002",
      "end_line": 8,
      "heading": "使用方式",
      "keywords": [
        "docs",
        "md",
        "readme",
        "standards",
        "使用方式",
        "authoring",
        "markdown",
        "processes",
        "standard",
        "修改规范",
        "可直接阅",
        "增或修改",
        "应是可直",
        "或修改规",
        "接阅读的",
        "改规范时",
        "新增或修",
        "是可直接",
        "正文",
        "每篇规范"
      ],
      "relations": {
        "capabilities": [
          "docs",
          "standards"
        ],
        "framework": null,
        "kind": "readme",
        "language": "docs",
        "service": null
      },
      "source_path": "docs/standards/README.md",
      "start_line": 5,
      "summary": "使用方式 in docs/standards/README.md"
    },
    {
      "chunk_id": "docs.standards.README#chunk-003",
      "end_line": 15,
      "heading": "当前规范",
      "keywords": [
        "docs",
        "md",
        "readme",
        "standards",
        "当前规范",
        "decisions",
        "processes",
        "references",
        "rules",
        "决策记录",
        "参考资料",
        "流程",
        "规则正文"
      ],
      "relations": {
        "capabilities": [
          "docs",
          "standards"
        ],
        "framework": null,
        "kind": "readme",
        "language": "docs",
        "service": null
      },
      "source_path": "docs/standards/README.md",
      "start_line": 9,
      "summary": "当前规范 in docs/standards/README.md"
    },
    {
      "chunk_id": "docs.standards.README#chunk-004",
      "end_line": 26,
      "heading": "同步检查",
      "keywords": [
        "docs",
        "md",
        "readme",
        "standards",
        "同步检查",
        "brief",
        "check",
        "format",
        "generate",
        "memory",
        "powershell",
        "python",
        "tools",
        "从仓库根",
        "仓库根目",
        "修改本目",
        "前仓库没",
        "库根目录",
        "应从仓库",
        "当前仓库"
      ],
      "relations": {
        "capabilities": [
          "docs",
          "standards"
        ],
        "framework": null,
        "kind": "readme",
        "language": "docs",
        "service": null
      },
      "source_path": "docs/standards/README.md",
      "start_line": 16,
      "summary": "同步检查 in docs/standards/README.md"
    },
    {
      "chunk_id": "docs.standards.README#chunk-005",
      "end_line": 30,
      "heading": "治理入口",
      "keywords": [
        "docs",
        "md",
        "readme",
        "standards",
        "治理入口",
        "decisions",
        "flow",
        "processes",
        "rfc",
        "决策记录",
        "流程"
      ],
      "relations": {
        "capabilities": [
          "docs",
          "standards"
        ],
        "framework": null,
        "kind": "readme",
        "language": "docs",
        "service": null
      },
      "source_path": "docs/standards/README.md",
      "start_line": 27,
      "summary": "治理入口 in docs/standards/README.md"
    },
    {
      "chunk_id": "docs.standards.decisions.0002-rest-response-shape-no-null#chunk-001",
      "end_line": 2,
      "heading": "REST 响应字段禁止 null",
      "keywords": [
        "0002",
        "decisions",
        "docs",
        "md",
        "no",
        "null",
        "response",
        "rest",
        "shape",
        "standards",
        "响应字段禁止",
        "响应字段",
        "字段禁止",
        "应字段禁"
      ],
      "relations": {
        "capabilities": [
          "0002",
          "decisions",
          "docs",
          "null",
          "response",
          "rest",
          "shape",
          "standards"
        ],
        "framework": null,
        "kind": "decision",
        "language": "docs",
        "service": null
      },
      "source_path": "docs/standards/decisions/0002-rest-response-shape-no-null.md",
      "start_line": 1,
      "summary": "REST 响应字段禁止 null in docs/standards/decisions/0002-rest-response-shape-no-null.md"
    },
    {
      "chunk_id": "docs.standards.decisions.0002-rest-response-shape-no-null#chunk-002",
      "end_line": 6,
      "heading": "背景",
      "keywords": [
        "0002",
        "decisions",
        "docs",
        "md",
        "no",
        "null",
        "response",
        "rest",
        "shape",
        "standards",
        "api",
        "rules",
        "保持一致",
        "减少客户",
        "响应需要",
        "客户端空",
        "少客户端",
        "并与",
        "应需要减",
        "户端空值"
      ],
      "relations": {
        "capabilities": [
          "0002",
          "decisions",
          "docs",
          "null",
          "response",
          "rest",
          "shape",
          "standards"
        ],
        "framework": null,
        "kind": "decision",
        "language": "docs",
        "service": null
      },
      "source_path": "docs/standards/decisions/0002-rest-response-shape-no-null.md",
      "start_line": 3,
      "summary": "背景 in docs/standards/decisions/0002-rest-response-shape-no-null.md"
    },
    {
      "chunk_id": "docs.standards.decisions.0002-rest-response-shape-no-null#chunk-003",
      "end_line": 10,
      "heading": "决策",
      "keywords": [
        "0002",
        "decisions",
        "docs",
        "md",
        "no",
        "null",
        "response",
        "rest",
        "shape",
        "standards",
        "api",
        "使用空集",
        "决策",
        "响应字段",
        "字段不返",
        "字段省略",
        "应字段不",
        "或明确错",
        "明确错误",
        "段不返回"
      ],
      "relations": {
        "capabilities": [
          "0002",
          "decisions",
          "docs",
          "null",
          "response",
          "rest",
          "shape",
          "standards"
        ],
        "framework": null,
        "kind": "decision",
        "language": "docs",
        "service": null
      },
      "source_path": "docs/standards/decisions/0002-rest-response-shape-no-null.md",
      "start_line": 7,
      "summary": "决策 in docs/standards/decisions/0002-rest-response-shape-no-null.md"
    },
    {
      "chunk_id": "docs.standards.decisions.0002-rest-response-shape-no-null#chunk-004",
      "end_line": 14,
      "heading": "影响",
      "keywords": [
        "0002",
        "decisions",
        "docs",
        "md",
        "no",
        "null",
        "response",
        "rest",
        "shape",
        "standards",
        "但服务端",
        "列化前明",
        "前明确空",
        "务端必须",
        "化前明确",
        "在序列化",
        "处理更稳",
        "客户端处",
        "序列化前",
        "影响"
      ],
      "relations": {
        "capabilities": [
          "0002",
          "decisions",
          "docs",
          "null",
          "response",
          "rest",
          "shape",
          "standards"
        ],
        "framework": null,
        "kind": "decision",
        "language": "docs",
        "service": null
      },
      "source_path": "docs/standards/decisions/0002-rest-response-shape-no-null.md",
      "start_line": 11,
      "summary": "影响 in docs/standards/decisions/0002-rest-response-shape-no-null.md"
    },
    {
      "chunk_id": "docs.standards.decisions.0002-rest-response-shape-no-null#chunk-005",
      "end_line": 18,
      "heading": "备选方案",
      "keywords": [
        "0002",
        "decisions",
        "docs",
        "md",
        "no",
        "null",
        "response",
        "rest",
        "shape",
        "standards",
        "备选方案",
        "会把兼容",
        "允许",
        "兼容成本",
        "嫁给所有",
        "容成本转",
        "成本转嫁",
        "所有客户",
        "把兼容成",
        "有客户端"
      ],
      "relations": {
        "capabilities": [
          "0002",
          "decisions",
          "docs",
          "null",
          "response",
          "rest",
          "shape",
          "standards"
        ],
        "framework": null,
        "kind": "decision",
        "language": "docs",
        "service": null
      },
      "source_path": "docs/standards/decisions/0002-rest-response-shape-no-null.md",
      "start_line": 15,
      "summary": "备选方案 in docs/standards/decisions/0002-rest-response-shape-no-null.md"
    },
    {
      "chunk_id": "docs.standards.decisions.0002-rest-response-shape-no-null#chunk-006",
      "end_line": 23,
      "heading": "变更记录",
      "keywords": [
        "0002",
        "decisions",
        "docs",
        "md",
        "no",
        "null",
        "response",
        "rest",
        "shape",
        "standards",
        "变更记录",
        "初始决策",
        "录初始决",
        "日期",
        "版本",
        "记录初始",
        "说明"
      ],
      "relations": {
        "capabilities": [
          "0002",
          "decisions",
          "docs",
          "null",
          "response",
          "rest",
          "shape",
          "standards"
        ],
        "framework": null,
        "kind": "decision",
        "language": "docs",
        "service": null
      },
      "source_path": "docs/standards/decisions/0002-rest-response-shape-no-null.md",
      "start_line": 19,
      "summary": "变更记录 in docs/standards/decisions/0002-rest-response-shape-no-null.md"
    },
    {
      "chunk_id": "docs.standards.processes.change-governance#chunk-001",
      "end_line": 2,
      "heading": "变更治理规范",
      "keywords": [
        "change",
        "docs",
        "governance",
        "md",
        "processes",
        "standards",
        "变更治理规范",
        "变更治理",
        "更治理规",
        "治理规范"
      ],
      "relations": {
        "capabilities": [
          "change",
          "docs",
          "governance",
          "processes",
          "standards"
        ],
        "framework": null,
        "kind": "process",
        "language": "docs",
        "service": null
      },
      "source_path": "docs/standards/processes/change-governance.md",
      "start_line": 1,
      "summary": "变更治理规范 in docs/standards/processes/change-governance.md"
    },
    {
      "chunk_id": "docs.standards.processes.change-governance#chunk-002",
      "end_line": 6,
      "heading": "目标",
      "keywords": [
        "change",
        "docs",
        "governance",
        "md",
        "processes",
        "standards",
        "保工程变",
        "变更有明",
        "和回退方",
        "回退方案",
        "工程变更",
        "影响评估",
        "径和回退",
        "明确影响",
        "更有明确",
        "有明确影",
        "沟通路径",
        "版本策略",
        "目标",
        "确保工程"
      ],
      "relations": {
        "capabilities": [
          "change",
          "docs",
          "governance",
          "processes",
          "standards"
        ],
        "framework": null,
        "kind": "process",
        "language": "docs",
        "service": null
      },
      "source_path": "docs/standards/processes/change-governance.md",
      "start_line": 3,
      "summary": "目标 in docs/standards/processes/change-governance.md"
    },
    {
      "chunk_id": "docs.standards.processes.change-governance#chunk-003",
      "end_line": 10,
      "heading": "适用范围",
      "keywords": [
        "change",
        "docs",
        "governance",
        "md",
        "processes",
        "standards",
        "适用范围",
        "api",
        "于标准文",
        "公共",
        "则和跨团",
        "和跨团队",
        "团队依赖",
        "基础设施",
        "标准文档",
        "用于标准",
        "础设施模",
        "规则和跨",
        "设施模板",
        "跨团队依"
      ],
      "relations": {
        "capabilities": [
          "change",
          "docs",
          "governance",
          "processes",
          "standards"
        ],
        "framework": null,
        "kind": "process",
        "language": "docs",
        "service": null
      },
      "source_path": "docs/standards/processes/change-governance.md",
      "start_line": 7,
      "summary": "适用范围 in docs/standards/processes/change-governance.md"
    },
    {
      "chunk_id": "docs.standards.processes.change-governance#chunk-004",
      "end_line": 18,
      "heading": "流程",
      "keywords": [
        "change",
        "docs",
        "governance",
        "md",
        "processes",
        "standards",
        "估兼容性",
        "兼容性和",
        "分类变更",
        "受影响团",
        "变更级别",
        "和迁移成",
        "容性和迁",
        "影响团队",
        "性和迁移",
        "新版本和",
        "更新版本",
        "本和索引",
        "流程",
        "版本和索"
      ],
      "relations": {
        "capabilities": [
          "change",
          "docs",
          "governance",
          "processes",
          "standards"
        ],
        "framework": null,
        "kind": "process",
        "language": "docs",
        "service": null
      },
      "source_path": "docs/standards/processes/change-governance.md",
      "start_line": 11,
      "summary": "流程 in docs/standards/processes/change-governance.md"
    },
    {
      "chunk_id": "docs.standards.processes.change-governance#chunk-005",
      "end_line": 22,
      "heading": "规则",
      "keywords": [
        "change",
        "docs",
        "governance",
        "md",
        "processes",
        "standards",
        "也必须更",
        "兼容性变",
        "出迁移窗",
        "变更也必",
        "变更必须",
        "坏性变更",
        "容性变更",
        "必须更新",
        "必须给出",
        "性变更也",
        "性变更必",
        "更也必须",
        "更必须给",
        "更新变更"
      ],
      "relations": {
        "capabilities": [
          "change",
          "docs",
          "governance",
          "processes",
          "standards"
        ],
        "framework": null,
        "kind": "process",
        "language": "docs",
        "service": null
      },
      "source_path": "docs/standards/processes/change-governance.md",
      "start_line": 19,
      "summary": "规则 in docs/standards/processes/change-governance.md"
    },
    {
      "chunk_id": "docs.standards.processes.change-governance#chunk-006",
      "end_line": 28,
      "heading": "检查清单",
      "keywords": [
        "change",
        "docs",
        "governance",
        "md",
        "processes",
        "standards",
        "检查清单",
        "否更新版",
        "否说明影",
        "否运行标",
        "影响范围",
        "新版本号",
        "明影响范",
        "是否更新",
        "是否说明",
        "是否运行",
        "更新版本",
        "标准检查",
        "行标准检",
        "说明影响"
      ],
      "relations": {
        "capabilities": [
          "change",
          "docs",
          "governance",
          "processes",
          "standards"
        ],
        "framework": null,
        "kind": "process",
        "language": "docs",
        "service": null
      },
      "source_path": "docs/standards/processes/change-governance.md",
      "start_line": 23,
      "summary": "检查清单 in docs/standards/processes/change-governance.md"
    },
    {
      "chunk_id": "docs.standards.processes.change-governance#chunk-007",
      "end_line": 33,
      "heading": "变更记录",
      "keywords": [
        "change",
        "docs",
        "governance",
        "md",
        "processes",
        "standards",
        "变更记录",
        "变更治理",
        "建立变更",
        "日期",
        "更治理流",
        "治理流程",
        "版本",
        "立变更治",
        "说明"
      ],
      "relations": {
        "capabilities": [
          "change",
          "docs",
          "governance",
          "processes",
          "standards"
        ],
        "framework": null,
        "kind": "process",
        "language": "docs",
        "service": null
      },
      "source_path": "docs/standards/processes/change-governance.md",
      "start_line": 29,
      "summary": "变更记录 in docs/standards/processes/change-governance.md"
    },
    {
      "chunk_id": "docs.standards.processes.dependency-onboarding#chunk-001",
      "end_line": 2,
      "heading": "依赖引入流程",
      "keywords": [
        "dependency",
        "docs",
        "md",
        "onboarding",
        "processes",
        "standards",
        "依赖引入流程",
        "依赖引入",
        "引入流程",
        "赖引入流"
      ],
      "relations": {
        "capabilities": [
          "dependency",
          "docs",
          "onboarding",
          "processes",
          "standards"
        ],
        "framework": null,
        "kind": "process",
        "language": "docs",
        "service": null
      },
      "source_path": "docs/standards/processes/dependency-onboarding.md",
      "start_line": 1,
      "summary": "依赖引入流程 in docs/standards/processes/dependency-onboarding.md"
    },
    {
      "chunk_id": "docs.standards.processes.dependency-onboarding#chunk-002",
      "end_line": 6,
      "heading": "目标",
      "keywords": [
        "dependency",
        "docs",
        "md",
        "onboarding",
        "processes",
        "standards",
        "于让跨团",
        "依赖引入",
        "入流程用",
        "具备明确",
        "动具备明",
        "团队工程",
        "备明确入",
        "工程活动",
        "引入流程",
        "明确入口",
        "活动具备",
        "流程用于",
        "用于让跨",
        "目标"
      ],
      "relations": {
        "capabilities": [
          "dependency",
          "docs",
          "onboarding",
          "processes",
          "standards"
        ],
        "framework": null,
        "kind": "process",
        "language": "docs",
        "service": null
      },
      "source_path": "docs/standards/processes/dependency-onboarding.md",
      "start_line": 3,
      "summary": "目标 in docs/standards/processes/dependency-onboarding.md"
    },
    {
      "chunk_id": "docs.standards.processes.dependency-onboarding#chunk-003",
      "end_line": 10,
      "heading": "适用范围",
      "keywords": [
        "dependency",
        "docs",
        "md",
        "onboarding",
        "processes",
        "standards",
        "适用范围",
        "于标准文",
        "依赖引入",
        "具配置和",
        "和工程流",
        "工具配置",
        "工程流程",
        "标准文档",
        "流程变更",
        "用于标准",
        "程流程变",
        "置和工程",
        "适用于标",
        "配置和工"
      ],
      "relations": {
        "capabilities": [
          "dependency",
          "docs",
          "onboarding",
          "processes",
          "standards"
        ],
        "framework": null,
        "kind": "process",
        "language": "docs",
        "service": null
      },
      "source_path": "docs/standards/processes/dependency-onboarding.md",
      "start_line": 7,
      "summary": "适用范围 in docs/standards/processes/dependency-onboarding.md"
    },
    {
      "chunk_id": "docs.standards.processes.dependency-onboarding#chunk-004",
      "end_line": 17,
      "heading": "流程",
      "keywords": [
        "dependency",
        "docs",
        "md",
        "onboarding",
        "processes",
        "standards",
        "别受影响",
        "受影响系",
        "和后续责",
        "响系统和",
        "完成评审",
        "审和验证",
        "影响系统",
        "成评审和",
        "明背景和",
        "景和目标",
        "本和后续",
        "流程",
        "版本和后",
        "系统和角"
      ],
      "relations": {
        "capabilities": [
          "dependency",
          "docs",
          "onboarding",
          "processes",
          "standards"
        ],
        "framework": null,
        "kind": "process",
        "language": "docs",
        "service": null
      },
      "source_path": "docs/standards/processes/dependency-onboarding.md",
      "start_line": 11,
      "summary": "流程 in docs/standards/processes/dependency-onboarding.md"
    },
    {
      "chunk_id": "docs.standards.processes.dependency-onboarding#chunk-005",
      "end_line": 21,
      "heading": "规则",
      "keywords": [
        "dependency",
        "docs",
        "md",
        "onboarding",
        "processes",
        "standards",
        "中的关键",
        "例外必须",
        "关键结论",
        "原因和到",
        "和到期时",
        "因和到期",
        "外必须说",
        "必须可追",
        "必须说明",
        "明原因和",
        "流程中的",
        "的关键结",
        "程中的关",
        "结论必须"
      ],
      "relations": {
        "capabilities": [
          "dependency",
          "docs",
          "onboarding",
          "processes",
          "standards"
        ],
        "framework": null,
        "kind": "process",
        "language": "docs",
        "service": null
      },
      "source_path": "docs/standards/processes/dependency-onboarding.md",
      "start_line": 18,
      "summary": "规则 in docs/standards/processes/dependency-onboarding.md"
    },
    {
      "chunk_id": "docs.standards.processes.dependency-onboarding#chunk-006",
      "end_line": 27,
      "heading": "检查清单",
      "keywords": [
        "dependency",
        "docs",
        "md",
        "onboarding",
        "processes",
        "standards",
        "检查清单",
        "令或验收",
        "入和输出",
        "否完成必",
        "否明确输",
        "否记录验",
        "命令或验",
        "完成必要",
        "录验证命",
        "必要评审",
        "成必要评",
        "明确输入",
        "是否完成",
        "是否明确"
      ],
      "relations": {
        "capabilities": [
          "dependency",
          "docs",
          "onboarding",
          "processes",
          "standards"
        ],
        "framework": null,
        "kind": "process",
        "language": "docs",
        "service": null
      },
      "source_path": "docs/standards/processes/dependency-onboarding.md",
      "start_line": 22,
      "summary": "检查清单 in docs/standards/processes/dependency-onboarding.md"
    },
    {
      "chunk_id": "docs.standards.processes.dependency-onboarding#chunk-007",
      "end_line": 32,
      "heading": "变更记录",
      "keywords": [
        "dependency",
        "docs",
        "md",
        "onboarding",
        "processes",
        "standards",
        "变更记录",
        "建立流程",
        "日期",
        "流程规范",
        "版本",
        "立流程规",
        "说明"
      ],
      "relations": {
        "capabilities": [
          "dependency",
          "docs",
          "onboarding",
          "processes",
          "standards"
        ],
        "framework": null,
        "kind": "process",
        "language": "docs",
        "service": null
      },
      "source_path": "docs/standards/processes/dependency-onboarding.md",
      "start_line": 28,
      "summary": "变更记录 in docs/standards/processes/dependency-onboarding.md"
    },
    {
      "chunk_id": "docs.standards.processes.doc-authoring#chunk-001",
      "end_line": 2,
      "heading": "文档撰写流程",
      "keywords": [
        "authoring",
        "doc",
        "docs",
        "md",
        "processes",
        "standards",
        "文档撰写流程",
        "撰写流程",
        "文档撰写",
        "档撰写流"
      ],
      "relations": {
        "capabilities": [
          "authoring",
          "doc",
          "docs",
          "processes",
          "standards"
        ],
        "framework": null,
        "kind": "process",
        "language": "docs",
        "service": null
      },
      "source_path": "docs/standards/processes/doc-authoring.md",
      "start_line": 1,
      "summary": "文档撰写流程 in docs/standards/processes/doc-authoring.md"
    },
    {
      "chunk_id": "docs.standards.processes.doc-authoring#chunk-002",
      "end_line": 6,
      "heading": "目标",
      "keywords": [
        "authoring",
        "doc",
        "docs",
        "md",
        "processes",
        "standards",
        "于让跨团",
        "具备明确",
        "写流程用",
        "动具备明",
        "团队工程",
        "备明确入",
        "工程活动",
        "撰写流程",
        "文档撰写",
        "明确入口",
        "档撰写流",
        "活动具备",
        "流程用于",
        "用于让跨"
      ],
      "relations": {
        "capabilities": [
          "authoring",
          "doc",
          "docs",
          "processes",
          "standards"
        ],
        "framework": null,
        "kind": "process",
        "language": "docs",
        "service": null
      },
      "source_path": "docs/standards/processes/doc-authoring.md",
      "start_line": 3,
      "summary": "目标 in docs/standards/processes/doc-authoring.md"
    },
    {
      "chunk_id": "docs.standards.processes.doc-authoring#chunk-003",
      "end_line": 10,
      "heading": "适用范围",
      "keywords": [
        "authoring",
        "doc",
        "docs",
        "md",
        "processes",
        "standards",
        "适用范围",
        "于标准文",
        "依赖引入",
        "具配置和",
        "和工程流",
        "工具配置",
        "工程流程",
        "标准文档",
        "流程变更",
        "用于标准",
        "程流程变",
        "置和工程",
        "适用于标",
        "配置和工"
      ],
      "relations": {
        "capabilities": [
          "authoring",
          "doc",
          "docs",
          "processes",
          "standards"
        ],
        "framework": null,
        "kind": "process",
        "language": "docs",
        "service": null
      },
      "source_path": "docs/standards/processes/doc-authoring.md",
      "start_line": 7,
      "summary": "适用范围 in docs/standards/processes/doc-authoring.md"
    },
    {
      "chunk_id": "docs.standards.processes.doc-authoring#chunk-004",
      "end_line": 17,
      "heading": "流程",
      "keywords": [
        "authoring",
        "doc",
        "docs",
        "md",
        "processes",
        "standards",
        "别受影响",
        "受影响系",
        "和后续责",
        "响系统和",
        "完成评审",
        "审和验证",
        "影响系统",
        "成评审和",
        "明背景和",
        "景和目标",
        "本和后续",
        "流程",
        "版本和后",
        "系统和角"
      ],
      "relations": {
        "capabilities": [
          "authoring",
          "doc",
          "docs",
          "processes",
          "standards"
        ],
        "framework": null,
        "kind": "process",
        "language": "docs",
        "service": null
      },
      "source_path": "docs/standards/processes/doc-authoring.md",
      "start_line": 11,
      "summary": "流程 in docs/standards/processes/doc-authoring.md"
    },
    {
      "chunk_id": "docs.standards.processes.doc-authoring#chunk-005",
      "end_line": 21,
      "heading": "规则",
      "keywords": [
        "authoring",
        "doc",
        "docs",
        "md",
        "processes",
        "standards",
        "中的关键",
        "例外必须",
        "关键结论",
        "原因和到",
        "和到期时",
        "因和到期",
        "外必须说",
        "必须可追",
        "必须说明",
        "明原因和",
        "流程中的",
        "的关键结",
        "程中的关",
        "结论必须"
      ],
      "relations": {
        "capabilities": [
          "authoring",
          "doc",
          "docs",
          "processes",
          "standards"
        ],
        "framework": null,
        "kind": "process",
        "language": "docs",
        "service": null
      },
      "source_path": "docs/standards/processes/doc-authoring.md",
      "start_line": 18,
      "summary": "规则 in docs/standards/processes/doc-authoring.md"
    },
    {
      "chunk_id": "docs.standards.processes.doc-authoring#chunk-006",
      "end_line": 27,
      "heading": "检查清单",
      "keywords": [
        "authoring",
        "doc",
        "docs",
        "md",
        "processes",
        "standards",
        "检查清单",
        "令或验收",
        "入和输出",
        "否完成必",
        "否明确输",
        "否记录验",
        "命令或验",
        "完成必要",
        "录验证命",
        "必要评审",
        "成必要评",
        "明确输入",
        "是否完成",
        "是否明确"
      ],
      "relations": {
        "capabilities": [
          "authoring",
          "doc",
          "docs",
          "processes",
          "standards"
        ],
        "framework": null,
        "kind": "process",
        "language": "docs",
        "service": null
      },
      "source_path": "docs/standards/processes/doc-authoring.md",
      "start_line": 22,
      "summary": "检查清单 in docs/standards/processes/doc-authoring.md"
    },
    {
      "chunk_id": "docs.standards.processes.doc-authoring#chunk-007",
      "end_line": 32,
      "heading": "变更记录",
      "keywords": [
        "authoring",
        "doc",
        "docs",
        "md",
        "processes",
        "standards",
        "变更记录",
        "建立流程",
        "日期",
        "流程规范",
        "版本",
        "立流程规",
        "说明"
      ],
      "relations": {
        "capabilities": [
          "authoring",
          "doc",
          "docs",
          "processes",
          "standards"
        ],
        "framework": null,
        "kind": "process",
        "language": "docs",
        "service": null
      },
      "source_path": "docs/standards/processes/doc-authoring.md",
      "start_line": 28,
      "summary": "变更记录 in docs/standards/processes/doc-authoring.md"
    },
    {
      "chunk_id": "docs.standards.processes.rfc-flow#chunk-001",
      "end_line": 2,
      "heading": "RFC 流程规范",
      "keywords": [
        "docs",
        "flow",
        "md",
        "processes",
        "rfc",
        "standards",
        "流程规范"
      ],
      "relations": {
        "capabilities": [
          "docs",
          "flow",
          "processes",
          "rfc",
          "standards"
        ],
        "framework": null,
        "kind": "process",
        "language": "docs",
        "service": null
      },
      "source_path": "docs/standards/processes/rfc-flow.md",
      "start_line": 1,
      "summary": "RFC 流程规范 in docs/standards/processes/rfc-flow.md"
    },
    {
      "chunk_id": "docs.standards.processes.rfc-flow#chunk-002",
      "end_line": 6,
      "heading": "目标",
      "keywords": [
        "docs",
        "flow",
        "md",
        "processes",
        "rfc",
        "standards",
        "前形成可",
        "变更在实",
        "可追踪的",
        "团队或高",
        "在实施前",
        "实施前形",
        "工程变更",
        "形成可讨",
        "成可讨论",
        "或高风险",
        "施前形成",
        "更在实施",
        "目标",
        "程变更在"
      ],
      "relations": {
        "capabilities": [
          "docs",
          "flow",
          "processes",
          "rfc",
          "standards"
        ],
        "framework": null,
        "kind": "process",
        "language": "docs",
        "service": null
      },
      "source_path": "docs/standards/processes/rfc-flow.md",
      "start_line": 3,
      "summary": "目标 in docs/standards/processes/rfc-flow.md"
    },
    {
      "chunk_id": "docs.standards.processes.rfc-flow#chunk-003",
      "end_line": 10,
      "heading": "适用范围",
      "keywords": [
        "docs",
        "flow",
        "md",
        "processes",
        "rfc",
        "standards",
        "适用范围",
        "于架构调",
        "体系演进",
        "公共契约",
        "共契约变",
        "变更和规",
        "和规范体",
        "基础设施",
        "契约变化",
        "施变更和",
        "更和规范",
        "架构调整",
        "用于架构",
        "础设施变"
      ],
      "relations": {
        "capabilities": [
          "docs",
          "flow",
          "processes",
          "rfc",
          "standards"
        ],
        "framework": null,
        "kind": "process",
        "language": "docs",
        "service": null
      },
      "source_path": "docs/standards/processes/rfc-flow.md",
      "start_line": 7,
      "summary": "适用范围 in docs/standards/processes/rfc-flow.md"
    },
    {
      "chunk_id": "docs.standards.processes.rfc-flow#chunk-004",
      "end_line": 17,
      "heading": "流程",
      "keywords": [
        "docs",
        "flow",
        "md",
        "processes",
        "rfc",
        "standards",
        "出备选方",
        "出背景和",
        "列出备选",
        "受影响角",
        "响角色评",
        "备选方案",
        "录结论并",
        "影响角色",
        "提出背景",
        "方案和取",
        "景和目标",
        "案和取舍",
        "流程",
        "结论并跟"
      ],
      "relations": {
        "capabilities": [
          "docs",
          "flow",
          "processes",
          "rfc",
          "standards"
        ],
        "framework": null,
        "kind": "process",
        "language": "docs",
        "service": null
      },
      "source_path": "docs/standards/processes/rfc-flow.md",
      "start_line": 11,
      "summary": "流程 in docs/standards/processes/rfc-flow.md"
    },
    {
      "chunk_id": "docs.standards.processes.rfc-flow#chunk-005",
      "end_line": 21,
      "heading": "模板",
      "keywords": [
        "docs",
        "flow",
        "md",
        "processes",
        "rfc",
        "standards",
        "包含背景",
        "和验收标",
        "少包含背",
        "式和验收",
        "影响范围",
        "方式和验",
        "方案",
        "模板",
        "目标",
        "移方式和",
        "至少包含",
        "迁移方式",
        "非目标",
        "验收标准"
      ],
      "relations": {
        "capabilities": [
          "docs",
          "flow",
          "processes",
          "rfc",
          "standards"
        ],
        "framework": null,
        "kind": "process",
        "language": "docs",
        "service": null
      },
      "source_path": "docs/standards/processes/rfc-flow.md",
      "start_line": 18,
      "summary": "模板 in docs/standards/processes/rfc-flow.md"
    },
    {
      "chunk_id": "docs.standards.processes.rfc-flow#chunk-006",
      "end_line": 27,
      "heading": "检查清单",
      "keywords": [
        "docs",
        "flow",
        "md",
        "processes",
        "rfc",
        "standards",
        "检查清单",
        "出受影响",
        "列出受影",
        "受影响系",
        "否列出受",
        "否明确非",
        "否说明回",
        "回滚或迁",
        "影响系统",
        "或迁移方",
        "明回滚或",
        "明确非目",
        "是否列出",
        "是否明确"
      ],
      "relations": {
        "capabilities": [
          "docs",
          "flow",
          "processes",
          "rfc",
          "standards"
        ],
        "framework": null,
        "kind": "process",
        "language": "docs",
        "service": null
      },
      "source_path": "docs/standards/processes/rfc-flow.md",
      "start_line": 22,
      "summary": "检查清单 in docs/standards/processes/rfc-flow.md"
    },
    {
      "chunk_id": "docs.standards.processes.rfc-flow#chunk-007",
      "end_line": 32,
      "heading": "变更记录",
      "keywords": [
        "docs",
        "flow",
        "md",
        "processes",
        "rfc",
        "standards",
        "变更记录",
        "建立",
        "日期",
        "流程",
        "版本",
        "说明"
      ],
      "relations": {
        "capabilities": [
          "docs",
          "flow",
          "processes",
          "rfc",
          "standards"
        ],
        "framework": null,
        "kind": "process",
        "language": "docs",
        "service": null
      },
      "source_path": "docs/standards/processes/rfc-flow.md",
      "start_line": 28,
      "summary": "变更记录 in docs/standards/processes/rfc-flow.md"
    },
    {
      "chunk_id": "docs.standards.processes.standard-authoring#chunk-001",
      "end_line": 2,
      "heading": "规范撰写规范",
      "keywords": [
        "authoring",
        "docs",
        "md",
        "processes",
        "standard",
        "standards",
        "规范撰写规范",
        "撰写规范",
        "范撰写规",
        "规范撰写"
      ],
      "relations": {
        "capabilities": [
          "authoring",
          "docs",
          "processes",
          "standard",
          "standards"
        ],
        "framework": null,
        "kind": "process",
        "language": "docs",
        "service": null
      },
      "source_path": "docs/standards/processes/standard-authoring.md",
      "start_line": 1,
      "summary": "规范撰写规范 in docs/standards/processes/standard-authoring.md"
    },
    {
      "chunk_id": "docs.standards.processes.standard-authoring#chunk-002",
      "end_line": 6,
      "heading": "目标",
      "keywords": [
        "authoring",
        "docs",
        "md",
        "processes",
        "standard",
        "standards",
        "义工程规",
        "定义工程",
        "工程规范",
        "引用方式",
        "文档的最",
        "方式和变",
        "最小结构",
        "本规范定",
        "档的最小",
        "用方式和",
        "的最小结",
        "目标",
        "程规范文",
        "章节组织"
      ],
      "relations": {
        "capabilities": [
          "authoring",
          "docs",
          "processes",
          "standard",
          "standards"
        ],
        "framework": null,
        "kind": "process",
        "language": "docs",
        "service": null
      },
      "source_path": "docs/standards/processes/standard-authoring.md",
      "start_line": 3,
      "summary": "目标 in docs/standards/processes/standard-authoring.md"
    },
    {
      "chunk_id": "docs.standards.processes.standard-authoring#chunk-003",
      "end_line": 17,
      "heading": "适用范围",
      "keywords": [
        "authoring",
        "docs",
        "md",
        "processes",
        "standard",
        "standards",
        "适用范围",
        "decisions",
        "rules",
        "下正式资",
        "下的标准",
        "下的流程",
        "下的长期",
        "于以下正",
        "以下正式",
        "本规范适",
        "标准正文",
        "正式资料",
        "流程规范",
        "用于以下"
      ],
      "relations": {
        "capabilities": [
          "authoring",
          "docs",
          "processes",
          "standard",
          "standards"
        ],
        "framework": null,
        "kind": "process",
        "language": "docs",
        "service": null
      },
      "source_path": "docs/standards/processes/standard-authoring.md",
      "start_line": 7,
      "summary": "适用范围 in docs/standards/processes/standard-authoring.md"
    },
    {
      "chunk_id": "docs.standards.processes.standard-authoring#chunk-004",
      "end_line": 29,
      "heading": "文档结构",
      "keywords": [
        "authoring",
        "docs",
        "md",
        "processes",
        "standard",
        "standards",
        "文档结构",
        "markdown",
        "一个一级",
        "一级标题",
        "个一级标",
        "义清晰的",
        "二级标题",
        "以下结构",
        "包含以下",
        "含以下结",
        "并包含以",
        "必须使用",
        "文档必须",
        "晰的二级"
      ],
      "relations": {
        "capabilities": [
          "authoring",
          "docs",
          "processes",
          "standard",
          "standards"
        ],
        "framework": null,
        "kind": "process",
        "language": "docs",
        "service": null
      },
      "source_path": "docs/standards/processes/standard-authoring.md",
      "start_line": 18,
      "summary": "文档结构 in docs/standards/processes/standard-authoring.md"
    },
    {
      "chunk_id": "docs.standards.processes.standard-authoring#chunk-005",
      "end_line": 37,
      "heading": "状态管理",
      "keywords": [
        "authoring",
        "docs",
        "md",
        "processes",
        "standard",
        "standards",
        "状态管理",
        "rfc",
        "变更记录",
        "和变更记",
        "审结论和",
        "态通过目",
        "更记录管",
        "状态通过",
        "目录位置",
        "稿资料应",
        "结论和变",
        "范状态通",
        "草稿资料",
        "规范状态"
      ],
      "relations": {
        "capabilities": [
          "authoring",
          "docs",
          "processes",
          "standard",
          "standards"
        ],
        "framework": null,
        "kind": "process",
        "language": "docs",
        "service": null
      },
      "source_path": "docs/standards/processes/standard-authoring.md",
      "start_line": 30,
      "summary": "状态管理 in docs/standards/processes/standard-authoring.md"
    },
    {
      "chunk_id": "docs.standards.processes.standard-authoring#chunk-006",
      "end_line": 46,
      "heading": "引用要求",
      "keywords": [
        "authoring",
        "docs",
        "md",
        "processes",
        "standard",
        "standards",
        "引用要求",
        "markdown",
        "中的日期",
        "变更记录",
        "引用规范",
        "录中的日",
        "或变更记",
        "文件路径",
        "文档标题",
        "更记录中",
        "本或变更",
        "版本或变",
        "用版本或",
        "用规范结"
      ],
      "relations": {
        "capabilities": [
          "authoring",
          "docs",
          "processes",
          "standard",
          "standards"
        ],
        "framework": null,
        "kind": "process",
        "language": "docs",
        "service": null
      },
      "source_path": "docs/standards/processes/standard-authoring.md",
      "start_line": 38,
      "summary": "引用要求 in docs/standards/processes/standard-authoring.md"
    },
    {
      "chunk_id": "docs.standards.processes.standard-authoring#chunk-007",
      "end_line": 59,
      "heading": "变更流程",
      "keywords": [
        "authoring",
        "docs",
        "md",
        "processes",
        "standard",
        "standards",
        "变更流程",
        "rfc",
        "修改规范",
        "决策应补",
        "增或重大",
        "大修改规",
        "工程决策",
        "应先创建",
        "应补充决",
        "或重大修",
        "改规范时",
        "效的工程",
        "新增或重",
        "有效的工"
      ],
      "relations": {
        "capabilities": [
          "authoring",
          "docs",
          "processes",
          "standard",
          "standards"
        ],
        "framework": null,
        "kind": "process",
        "language": "docs",
        "service": null
      },
      "source_path": "docs/standards/processes/standard-authoring.md",
      "start_line": 47,
      "summary": "变更流程 in docs/standards/processes/standard-authoring.md"
    },
    {
      "chunk_id": "docs.standards.processes.standard-authoring#chunk-008",
      "end_line": 67,
      "heading": "变更记录",
      "keywords": [
        "authoring",
        "docs",
        "md",
        "processes",
        "standard",
        "standards",
        "变更记录",
        "front",
        "matter",
        "为纯人员",
        "人员阅读",
        "员阅读正",
        "和隐藏锚",
        "器字段和",
        "字段和隐",
        "改为纯人",
        "日期",
        "机器字段",
        "段和隐藏",
        "版本"
      ],
      "relations": {
        "capabilities": [
          "authoring",
          "docs",
          "processes",
          "standard",
          "standards"
        ],
        "framework": null,
        "kind": "process",
        "language": "docs",
        "service": null
      },
      "source_path": "docs/standards/processes/standard-authoring.md",
      "start_line": 60,
      "summary": "变更记录 in docs/standards/processes/standard-authoring.md"
    },
    {
      "chunk_id": "docs.standards.references.datetime#chunk-001",
      "end_line": 2,
      "heading": "日期时间参考",
      "keywords": [
        "datetime",
        "docs",
        "md",
        "references",
        "standards",
        "日期时间参考",
        "日期时间",
        "时间参考",
        "期时间参"
      ],
      "relations": {
        "capabilities": [
          "datetime",
          "docs",
          "references",
          "standards"
        ],
        "framework": null,
        "kind": "reference",
        "language": "docs",
        "service": null
      },
      "source_path": "docs/standards/references/datetime.md",
      "start_line": 1,
      "summary": "日期时间参考 in docs/standards/references/datetime.md"
    },
    {
      "chunk_id": "docs.standards.references.datetime#chunk-002",
      "end_line": 6,
      "heading": "目标",
      "keywords": [
        "datetime",
        "docs",
        "md",
        "references",
        "standards",
        "一日期时",
        "传输",
        "和测试断",
        "字段的存",
        "展示和测",
        "断言方式",
        "日期时间",
        "时间字段",
        "期时间字",
        "段的存储",
        "测试断言",
        "目标",
        "示和测试",
        "统一日期",
        "试断言方"
      ],
      "relations": {
        "capabilities": [
          "datetime",
          "docs",
          "references",
          "standards"
        ],
        "framework": null,
        "kind": "reference",
        "language": "docs",
        "service": null
      },
      "source_path": "docs/standards/references/datetime.md",
      "start_line": 3,
      "summary": "目标 in docs/standards/references/datetime.md"
    },
    {
      "chunk_id": "docs.standards.references.datetime#chunk-003",
      "end_line": 10,
      "heading": "适用范围",
      "keywords": [
        "datetime",
        "docs",
        "md",
        "references",
        "standards",
        "适用范围",
        "api",
        "中的统一",
        "和跨团队",
        "团队沟通",
        "控和跨团",
        "文档",
        "沟通中的",
        "测试",
        "的统一引",
        "监控和跨",
        "统一引用",
        "跨团队沟",
        "适用于",
        "通中的统"
      ],
      "relations": {
        "capabilities": [
          "datetime",
          "docs",
          "references",
          "standards"
        ],
        "framework": null,
        "kind": "reference",
        "language": "docs",
        "service": null
      },
      "source_path": "docs/standards/references/datetime.md",
      "start_line": 7,
      "summary": "适用范围 in docs/standards/references/datetime.md"
    },
    {
      "chunk_id": "docs.standards.references.datetime#chunk-004",
      "end_line": 18,
      "heading": "目录",
      "keywords": [
        "datetime",
        "docs",
        "md",
        "references",
        "standards",
        "iso",
        "utc",
        "yyyy",
        "不包含时",
        "前端按语",
        "包含时区",
        "包含时间",
        "含时区或",
        "地化格式",
        "场景",
        "日期字段",
        "本地化格",
        "机器传输",
        "标识",
        "格式"
      ],
      "relations": {
        "capabilities": [
          "datetime",
          "docs",
          "references",
          "standards"
        ],
        "framework": null,
        "kind": "reference",
        "language": "docs",
        "service": null
      },
      "source_path": "docs/standards/references/datetime.md",
      "start_line": 11,
      "summary": "目录 in docs/standards/references/datetime.md"
    },
    {
      "chunk_id": "docs.standards.references.datetime#chunk-005",
      "end_line": 24,
      "heading": "示例",
      "keywords": [
        "datetime",
        "docs",
        "md",
        "references",
        "standards",
        "一术语或",
        "不同团队",
        "中引用统",
        "反例",
        "同团队为",
        "在设计文",
        "引用统一",
        "态码含义",
        "或状态码",
        "文档中引",
        "术语或状",
        "档中引用",
        "正例",
        "状态码含",
        "用统一术"
      ],
      "relations": {
        "capabilities": [
          "datetime",
          "docs",
          "references",
          "standards"
        ],
        "framework": null,
        "kind": "reference",
        "language": "docs",
        "service": null
      },
      "source_path": "docs/standards/references/datetime.md",
      "start_line": 19,
      "summary": "示例 in docs/standards/references/datetime.md"
    },
    {
      "chunk_id": "docs.standards.references.datetime#chunk-006",
      "end_line": 29,
      "heading": "变更记录",
      "keywords": [
        "datetime",
        "docs",
        "md",
        "references",
        "standards",
        "变更记录",
        "参考目录",
        "建立参考",
        "日期",
        "版本",
        "立参考目",
        "说明"
      ],
      "relations": {
        "capabilities": [
          "datetime",
          "docs",
          "references",
          "standards"
        ],
        "framework": null,
        "kind": "reference",
        "language": "docs",
        "service": null
      },
      "source_path": "docs/standards/references/datetime.md",
      "start_line": 25,
      "summary": "变更记录 in docs/standards/references/datetime.md"
    },
    {
      "chunk_id": "docs.standards.references.error-codes#chunk-001",
      "end_line": 2,
      "heading": "错误码目录",
      "keywords": [
        "codes",
        "docs",
        "error",
        "md",
        "references",
        "standards",
        "错误码目录",
        "误码目录",
        "错误码目"
      ],
      "relations": {
        "capabilities": [
          "codes",
          "docs",
          "error",
          "references",
          "standards"
        ],
        "framework": null,
        "kind": "reference",
        "language": "docs",
        "service": null
      },
      "source_path": "docs/standards/references/error-codes.md",
      "start_line": 1,
      "summary": "错误码目录 in docs/standards/references/error-codes.md"
    },
    {
      "chunk_id": "docs.standards.references.error-codes#chunk-002",
      "end_line": 6,
      "heading": "目标",
      "keywords": [
        "codes",
        "docs",
        "error",
        "md",
        "references",
        "standards",
        "api",
        "供稳定的",
        "和用户提",
        "定的错误",
        "引用目录",
        "户提示提",
        "提供稳定",
        "提示提供",
        "测试和用",
        "用户提示",
        "的错误码",
        "目标",
        "码引用目",
        "示提供稳"
      ],
      "relations": {
        "capabilities": [
          "codes",
          "docs",
          "error",
          "references",
          "standards"
        ],
        "framework": null,
        "kind": "reference",
        "language": "docs",
        "service": null
      },
      "source_path": "docs/standards/references/error-codes.md",
      "start_line": 3,
      "summary": "目标 in docs/standards/references/error-codes.md"
    },
    {
      "chunk_id": "docs.standards.references.error-codes#chunk-003",
      "end_line": 10,
      "heading": "适用范围",
      "keywords": [
        "codes",
        "docs",
        "error",
        "md",
        "references",
        "standards",
        "适用范围",
        "api",
        "rest",
        "前端错误",
        "动化测试",
        "化测试断",
        "和运维排",
        "断言和运",
        "测试断言",
        "端错误处",
        "自动化测",
        "言和运维",
        "试断言和",
        "运维排障"
      ],
      "relations": {
        "capabilities": [
          "codes",
          "docs",
          "error",
          "references",
          "standards"
        ],
        "framework": null,
        "kind": "reference",
        "language": "docs",
        "service": null
      },
      "source_path": "docs/standards/references/error-codes.md",
      "start_line": 7,
      "summary": "适用范围 in docs/standards/references/error-codes.md"
    },
    {
      "chunk_id": "docs.standards.references.error-codes#chunk-004",
      "end_line": 19,
      "heading": "目录",
      "keywords": [
        "codes",
        "docs",
        "error",
        "md",
        "references",
        "standards",
        "auth",
        "field",
        "found",
        "required",
        "resource",
        "system",
        "unauthorized",
        "unavailable",
        "validation",
        "前缀",
        "场景",
        "目录",
        "示例",
        "系统错误"
      ],
      "relations": {
        "capabilities": [
          "codes",
          "docs",
          "error",
          "references",
          "standards"
        ],
        "framework": null,
        "kind": "reference",
        "language": "docs",
        "service": null
      },
      "source_path": "docs/standards/references/error-codes.md",
      "start_line": 11,
      "summary": "目录 in docs/standards/references/error-codes.md"
    },
    {
      "chunk_id": "docs.standards.references.error-codes#chunk-005",
      "end_line": 25,
      "heading": "示例",
      "keywords": [
        "codes",
        "docs",
        "error",
        "md",
        "references",
        "standards",
        "field",
        "required",
        "validation",
        "位表单项",
        "反例",
        "定位表单",
        "客户端根",
        "客户端解",
        "户端根据",
        "户端解析",
        "析自然语",
        "正例",
        "然语言错",
        "示例"
      ],
      "relations": {
        "capabilities": [
          "codes",
          "docs",
          "error",
          "references",
          "standards"
        ],
        "framework": null,
        "kind": "reference",
        "language": "docs",
        "service": null
      },
      "source_path": "docs/standards/references/error-codes.md",
      "start_line": 20,
      "summary": "示例 in docs/standards/references/error-codes.md"
    },
    {
      "chunk_id": "docs.standards.references.error-codes#chunk-006",
      "end_line": 30,
      "heading": "变更记录",
      "keywords": [
        "codes",
        "docs",
        "error",
        "md",
        "references",
        "standards",
        "变更记录",
        "建立错误",
        "日期",
        "版本",
        "立错误码",
        "误码目录",
        "说明",
        "错误码目"
      ],
      "relations": {
        "capabilities": [
          "codes",
          "docs",
          "error",
          "references",
          "standards"
        ],
        "framework": null,
        "kind": "reference",
        "language": "docs",
        "service": null
      },
      "source_path": "docs/standards/references/error-codes.md",
      "start_line": 26,
      "summary": "变更记录 in docs/standards/references/error-codes.md"
    },
    {
      "chunk_id": "docs.standards.references.glossary#chunk-001",
      "end_line": 2,
      "heading": "工程术语表",
      "keywords": [
        "docs",
        "glossary",
        "md",
        "references",
        "standards",
        "工程术语表",
        "工程术语",
        "程术语表"
      ],
      "relations": {
        "capabilities": [
          "docs",
          "glossary",
          "references",
          "standards"
        ],
        "framework": null,
        "kind": "reference",
        "language": "docs",
        "service": null
      },
      "source_path": "docs/standards/references/glossary.md",
      "start_line": 1,
      "summary": "工程术语表 in docs/standards/references/glossary.md"
    },
    {
      "chunk_id": "docs.standards.references.glossary#chunk-002",
      "end_line": 6,
      "heading": "目标",
      "keywords": [
        "docs",
        "glossary",
        "md",
        "references",
        "standards",
        "中的术语",
        "减少跨团",
        "团队沟通",
        "少跨团队",
        "术语歧义",
        "沟通中的",
        "的术语歧",
        "目标",
        "跨团队沟",
        "通中的术",
        "队沟通中"
      ],
      "relations": {
        "capabilities": [
          "docs",
          "glossary",
          "references",
          "standards"
        ],
        "framework": null,
        "kind": "reference",
        "language": "docs",
        "service": null
      },
      "source_path": "docs/standards/references/glossary.md",
      "start_line": 3,
      "summary": "目标 in docs/standards/references/glossary.md"
    },
    {
      "chunk_id": "docs.standards.references.glossary#chunk-003",
      "end_line": 10,
      "heading": "适用范围",
      "keywords": [
        "docs",
        "glossary",
        "md",
        "references",
        "standards",
        "适用范围",
        "api",
        "中的统一",
        "和跨团队",
        "团队沟通",
        "控和跨团",
        "文档",
        "沟通中的",
        "测试",
        "的统一引",
        "监控和跨",
        "统一引用",
        "跨团队沟",
        "适用于",
        "通中的统"
      ],
      "relations": {
        "capabilities": [
          "docs",
          "glossary",
          "references",
          "standards"
        ],
        "framework": null,
        "kind": "reference",
        "language": "docs",
        "service": null
      },
      "source_path": "docs/standards/references/glossary.md",
      "start_line": 7,
      "summary": "适用范围 in docs/standards/references/glossary.md"
    },
    {
      "chunk_id": "docs.standards.references.glossary#chunk-004",
      "end_line": 18,
      "heading": "目录",
      "keywords": [
        "docs",
        "glossary",
        "md",
        "references",
        "standards",
        "不要求既",
        "供方共同",
        "共同遵守",
        "兼容变更",
        "同遵守的",
        "含义",
        "和提供方",
        "契约",
        "守的接口",
        "接口承诺",
        "提供方共",
        "方共同遵",
        "方和提供",
        "术语",
        "用方和提"
      ],
      "relations": {
        "capabilities": [
          "docs",
          "glossary",
          "references",
          "standards"
        ],
        "framework": null,
        "kind": "reference",
        "language": "docs",
        "service": null
      },
      "source_path": "docs/standards/references/glossary.md",
      "start_line": 11,
      "summary": "目录 in docs/standards/references/glossary.md"
    },
    {
      "chunk_id": "docs.standards.references.glossary#chunk-005",
      "end_line": 24,
      "heading": "示例",
      "keywords": [
        "docs",
        "glossary",
        "md",
        "references",
        "standards",
        "一术语或",
        "不同团队",
        "中引用统",
        "反例",
        "同团队为",
        "在设计文",
        "引用统一",
        "态码含义",
        "或状态码",
        "文档中引",
        "术语或状",
        "档中引用",
        "正例",
        "状态码含",
        "用统一术"
      ],
      "relations": {
        "capabilities": [
          "docs",
          "glossary",
          "references",
          "standards"
        ],
        "framework": null,
        "kind": "reference",
        "language": "docs",
        "service": null
      },
      "source_path": "docs/standards/references/glossary.md",
      "start_line": 19,
      "summary": "示例 in docs/standards/references/glossary.md"
    },
    {
      "chunk_id": "docs.standards.references.glossary#chunk-006",
      "end_line": 29,
      "heading": "变更记录",
      "keywords": [
        "docs",
        "glossary",
        "md",
        "references",
        "standards",
        "变更记录",
        "参考目录",
        "建立参考",
        "日期",
        "版本",
        "立参考目",
        "说明"
      ],
      "relations": {
        "capabilities": [
          "docs",
          "glossary",
          "references",
          "standards"
        ],
        "framework": null,
        "kind": "reference",
        "language": "docs",
        "service": null
      },
      "source_path": "docs/standards/references/glossary.md",
      "start_line": 25,
      "summary": "变更记录 in docs/standards/references/glossary.md"
    },
    {
      "chunk_id": "docs.standards.references.http-status#chunk-001",
      "end_line": 2,
      "heading": "HTTP 状态码参考",
      "keywords": [
        "docs",
        "http",
        "md",
        "references",
        "standards",
        "status",
        "状态码参考",
        "态码参考",
        "状态码参"
      ],
      "relations": {
        "capabilities": [
          "docs",
          "http",
          "references",
          "standards",
          "status"
        ],
        "framework": null,
        "kind": "reference",
        "language": "docs",
        "service": null
      },
      "source_path": "docs/standards/references/http-status.md",
      "start_line": 1,
      "summary": "HTTP 状态码参考 in docs/standards/references/http-status.md"
    },
    {
      "chunk_id": "docs.standards.references.http-status#chunk-002",
      "end_line": 6,
      "heading": "目标",
      "keywords": [
        "docs",
        "http",
        "md",
        "references",
        "standards",
        "status",
        "api",
        "和客户端",
        "处理中的",
        "客户端处",
        "态码含义",
        "户端处理",
        "断言和客",
        "测试断言",
        "状态码含",
        "目标",
        "端处理中",
        "统一",
        "言和客户",
        "设计"
      ],
      "relations": {
        "capabilities": [
          "docs",
          "http",
          "references",
          "standards",
          "status"
        ],
        "framework": null,
        "kind": "reference",
        "language": "docs",
        "service": null
      },
      "source_path": "docs/standards/references/http-status.md",
      "start_line": 3,
      "summary": "目标 in docs/standards/references/http-status.md"
    },
    {
      "chunk_id": "docs.standards.references.http-status#chunk-003",
      "end_line": 10,
      "heading": "适用范围",
      "keywords": [
        "docs",
        "http",
        "md",
        "references",
        "standards",
        "status",
        "适用范围",
        "api",
        "中的统一",
        "和跨团队",
        "团队沟通",
        "控和跨团",
        "文档",
        "沟通中的",
        "测试",
        "的统一引",
        "监控和跨",
        "统一引用",
        "跨团队沟",
        "适用于"
      ],
      "relations": {
        "capabilities": [
          "docs",
          "http",
          "references",
          "standards",
          "status"
        ],
        "framework": null,
        "kind": "reference",
        "language": "docs",
        "service": null
      },
      "source_path": "docs/standards/references/http-status.md",
      "start_line": 7,
      "summary": "适用范围 in docs/standards/references/http-status.md"
    },
    {
      "chunk_id": "docs.standards.references.http-status#chunk-004",
      "end_line": 23,
      "heading": "目录",
      "keywords": [
        "docs",
        "http",
        "md",
        "references",
        "standards",
        "status",
        "入格式或",
        "创建成功",
        "回新资源",
        "回资源或",
        "场景",
        "成功查询",
        "新资源标",
        "标识或位",
        "源或结果",
        "源标识或",
        "状态码",
        "目录",
        "识或位置",
        "说明"
      ],
      "relations": {
        "capabilities": [
          "docs",
          "http",
          "references",
          "standards",
          "status"
        ],
        "framework": null,
        "kind": "reference",
        "language": "docs",
        "service": null
      },
      "source_path": "docs/standards/references/http-status.md",
      "start_line": 11,
      "summary": "目录 in docs/standards/references/http-status.md"
    },
    {
      "chunk_id": "docs.standards.references.http-status#chunk-005",
      "end_line": 29,
      "heading": "示例",
      "keywords": [
        "docs",
        "http",
        "md",
        "references",
        "standards",
        "status",
        "一术语或",
        "不同团队",
        "中引用统",
        "反例",
        "同团队为",
        "在设计文",
        "引用统一",
        "态码含义",
        "或状态码",
        "文档中引",
        "术语或状",
        "档中引用",
        "正例",
        "状态码含"
      ],
      "relations": {
        "capabilities": [
          "docs",
          "http",
          "references",
          "standards",
          "status"
        ],
        "framework": null,
        "kind": "reference",
        "language": "docs",
        "service": null
      },
      "source_path": "docs/standards/references/http-status.md",
      "start_line": 24,
      "summary": "示例 in docs/standards/references/http-status.md"
    },
    {
      "chunk_id": "docs.standards.references.http-status#chunk-006",
      "end_line": 34,
      "heading": "变更记录",
      "keywords": [
        "docs",
        "http",
        "md",
        "references",
        "standards",
        "status",
        "变更记录",
        "参考目录",
        "建立参考",
        "日期",
        "版本",
        "立参考目",
        "说明"
      ],
      "relations": {
        "capabilities": [
          "docs",
          "http",
          "references",
          "standards",
          "status"
        ],
        "framework": null,
        "kind": "reference",
        "language": "docs",
        "service": null
      },
      "source_path": "docs/standards/references/http-status.md",
      "start_line": 30,
      "summary": "变更记录 in docs/standards/references/http-status.md"
    },
    {
      "chunk_id": "docs.standards.rules.api-error-response#chunk-001",
      "end_line": 2,
      "heading": "API 错误响应规范",
      "keywords": [
        "api",
        "docs",
        "error",
        "md",
        "response",
        "rules",
        "standards",
        "错误响应规范",
        "响应规范",
        "误响应规",
        "错误响应"
      ],
      "relations": {
        "capabilities": [
          "api",
          "docs",
          "error",
          "response",
          "rules",
          "standards"
        ],
        "framework": null,
        "kind": "standard",
        "language": "docs",
        "service": null
      },
      "source_path": "docs/standards/rules/api-error-response.md",
      "start_line": 1,
      "summary": "API 错误响应规范 in docs/standards/rules/api-error-response.md"
    },
    {
      "chunk_id": "docs.standards.rules.api-error-response#chunk-002",
      "end_line": 6,
      "heading": "目标",
      "keywords": [
        "api",
        "docs",
        "error",
        "md",
        "response",
        "rules",
        "standards",
        "于降低客",
        "低客户端",
        "依赖异常",
        "务端泄露",
        "响应规范",
        "客户端依",
        "应规范用",
        "异常文本",
        "户端依赖",
        "服务端泄",
        "用于降低",
        "目标",
        "端依赖异"
      ],
      "relations": {
        "capabilities": [
          "api",
          "docs",
          "error",
          "response",
          "rules",
          "standards"
        ],
        "framework": null,
        "kind": "standard",
        "language": "docs",
        "service": null
      },
      "source_path": "docs/standards/rules/api-error-response.md",
      "start_line": 3,
      "summary": "目标 in docs/standards/rules/api-error-response.md"
    },
    {
      "chunk_id": "docs.standards.rules.api-error-response#chunk-003",
      "end_line": 10,
      "heading": "适用范围",
      "keywords": [
        "api",
        "docs",
        "error",
        "md",
        "response",
        "rules",
        "standards",
        "适用范围",
        "apps",
        "backend",
        "frontend",
        "json",
        "mobile",
        "mock",
        "open",
        "rest",
        "rpc",
        "services",
        "src",
        "单校验失"
      ],
      "relations": {
        "capabilities": [
          "api",
          "docs",
          "error",
          "response",
          "rules",
          "standards"
        ],
        "framework": null,
        "kind": "standard",
        "language": "docs",
        "service": null
      },
      "source_path": "docs/standards/rules/api-error-response.md",
      "start_line": 7,
      "summary": "适用范围 in docs/standards/rules/api-error-response.md"
    },
    {
      "chunk_id": "docs.standards.rules.api-error-response#chunk-004",
      "end_line": 20,
      "heading": "规则",
      "keywords": [
        "api",
        "docs",
        "error",
        "md",
        "response",
        "rules",
        "standards",
        "code",
        "json",
        "message",
        "trace",
        "使用稳定",
        "名和类型",
        "和类型不",
        "响应必须",
        "型不得随",
        "字段名和",
        "对象",
        "应必须使",
        "必须使用"
      ],
      "relations": {
        "capabilities": [
          "api",
          "docs",
          "error",
          "response",
          "rules",
          "standards"
        ],
        "framework": null,
        "kind": "standard",
        "language": "docs",
        "service": null
      },
      "source_path": "docs/standards/rules/api-error-response.md",
      "start_line": 11,
      "summary": "规则 in docs/standards/rules/api-error-response.md"
    },
    {
      "chunk_id": "docs.standards.rules.api-error-response#chunk-005",
      "end_line": 49,
      "heading": "示例",
      "keywords": [
        "api",
        "docs",
        "error",
        "md",
        "response",
        "rules",
        "standards",
        "af7651916cd43dd8448eb211c80319c",
        "code",
        "details",
        "failed",
        "field",
        "items",
        "json",
        "message",
        "min",
        "quantity",
        "trace",
        "validation",
        "value"
      ],
      "relations": {
        "capabilities": [
          "api",
          "docs",
          "error",
          "response",
          "rules",
          "standards"
        ],
        "framework": null,
        "kind": "standard",
        "language": "docs",
        "service": null
      },
      "source_path": "docs/standards/rules/api-error-response.md",
      "start_line": 21,
      "summary": "示例 in docs/standards/rules/api-error-response.md"
    },
    {
      "chunk_id": "docs.standards.rules.api-error-response#chunk-006",
      "end_line": 57,
      "heading": "检查清单",
      "keywords": [
        "api",
        "docs",
        "error",
        "md",
        "response",
        "rules",
        "standards",
        "检查清单",
        "code",
        "http",
        "message",
        "trace",
        "且字段类",
        "包含稳定",
        "否包含稳",
        "含稳定的",
        "响应是否",
        "字段类型",
        "应是否包",
        "是否包含"
      ],
      "relations": {
        "capabilities": [
          "api",
          "docs",
          "error",
          "response",
          "rules",
          "standards"
        ],
        "framework": null,
        "kind": "standard",
        "language": "docs",
        "service": null
      },
      "source_path": "docs/standards/rules/api-error-response.md",
      "start_line": 50,
      "summary": "检查清单 in docs/standards/rules/api-error-response.md"
    },
    {
      "chunk_id": "docs.standards.rules.api-error-response#chunk-007",
      "end_line": 65,
      "heading": "相关规范",
      "keywords": [
        "api",
        "docs",
        "error",
        "md",
        "response",
        "rules",
        "standards",
        "相关规范",
        "codes",
        "handling",
        "http",
        "references",
        "shape",
        "status",
        "tracing"
      ],
      "relations": {
        "capabilities": [
          "api",
          "docs",
          "error",
          "response",
          "rules",
          "standards"
        ],
        "framework": null,
        "kind": "standard",
        "language": "docs",
        "service": null
      },
      "source_path": "docs/standards/rules/api-error-response.md",
      "start_line": 58,
      "summary": "相关规范 in docs/standards/rules/api-error-response.md"
    },
    {
      "chunk_id": "docs.standards.rules.api-error-response#chunk-008",
      "end_line": 71,
      "heading": "变更记录",
      "keywords": [
        "api",
        "docs",
        "error",
        "md",
        "response",
        "rules",
        "standards",
        "变更记录",
        "充执行级",
        "初始规范",
        "单和相关",
        "和相关规",
        "建立初始",
        "执行级规",
        "日期",
        "查清单和",
        "检查清单",
        "清单和相",
        "版本",
        "相关规范"
      ],
      "relations": {
        "capabilities": [
          "api",
          "docs",
          "error",
          "response",
          "rules",
          "standards"
        ],
        "framework": null,
        "kind": "standard",
        "language": "docs",
        "service": null
      },
      "source_path": "docs/standards/rules/api-error-response.md",
      "start_line": 66,
      "summary": "变更记录 in docs/standards/rules/api-error-response.md"
    },
    {
      "chunk_id": "docs.standards.rules.api-response-shape#chunk-001",
      "end_line": 2,
      "heading": "API 统一响应结构",
      "keywords": [
        "api",
        "docs",
        "md",
        "response",
        "rules",
        "shape",
        "standards",
        "统一响应结构",
        "一响应结",
        "响应结构",
        "统一响应"
      ],
      "relations": {
        "capabilities": [
          "api",
          "docs",
          "response",
          "rules",
          "shape",
          "standards"
        ],
        "framework": null,
        "kind": "standard",
        "language": "docs",
        "service": null
      },
      "source_path": "docs/standards/rules/api-response-shape.md",
      "start_line": 1,
      "summary": "API 统一响应结构 in docs/standards/rules/api-response-shape.md"
    },
    {
      "chunk_id": "docs.standards.rules.api-response-shape#chunk-002",
      "end_line": 6,
      "heading": "目标",
      "keywords": [
        "api",
        "docs",
        "md",
        "response",
        "rules",
        "shape",
        "standards",
        "null",
        "rest",
        "web",
        "一响应结",
        "于降低客",
        "低客户端",
        "响应结构",
        "客户端针",
        "应结构用",
        "户端针对",
        "构用于降",
        "用于降低",
        "目标"
      ],
      "relations": {
        "capabilities": [
          "api",
          "docs",
          "response",
          "rules",
          "shape",
          "standards"
        ],
        "framework": null,
        "kind": "standard",
        "language": "docs",
        "service": null
      },
      "source_path": "docs/standards/rules/api-response-shape.md",
      "start_line": 3,
      "summary": "目标 in docs/standards/rules/api-response-shape.md"
    },
    {
      "chunk_id": "docs.standards.rules.api-response-shape#chunk-003",
      "end_line": 10,
      "heading": "适用范围",
      "keywords": [
        "api",
        "docs",
        "md",
        "response",
        "rules",
        "shape",
        "standards",
        "适用范围",
        "apps",
        "backend",
        "frontend",
        "json",
        "mobile",
        "open",
        "rest",
        "rpc",
        "services",
        "socket",
        "src",
        "web"
      ],
      "relations": {
        "capabilities": [
          "api",
          "docs",
          "response",
          "rules",
          "shape",
          "standards"
        ],
        "framework": null,
        "kind": "standard",
        "language": "docs",
        "service": null
      },
      "source_path": "docs/standards/rules/api-response-shape.md",
      "start_line": 7,
      "summary": "适用范围 in docs/standards/rules/api-response-shape.md"
    },
    {
      "chunk_id": "docs.standards.rules.api-response-shape#chunk-004",
      "end_line": 21,
      "heading": "规则",
      "keywords": [
        "api",
        "docs",
        "md",
        "response",
        "rules",
        "shape",
        "standards",
        "json",
        "一端点的",
        "不得在对",
        "功响应必",
        "同一端点",
        "响应必须",
        "对象",
        "层结构不",
        "应必须返",
        "必须返回",
        "成功响应",
        "构不得在",
        "点的顶层"
      ],
      "relations": {
        "capabilities": [
          "api",
          "docs",
          "response",
          "rules",
          "shape",
          "standards"
        ],
        "framework": null,
        "kind": "standard",
        "language": "docs",
        "service": null
      },
      "source_path": "docs/standards/rules/api-response-shape.md",
      "start_line": 11,
      "summary": "规则 in docs/standards/rules/api-response-shape.md"
    },
    {
      "chunk_id": "docs.standards.rules.api-response-shape#chunk-005",
      "end_line": 46,
      "heading": "示例",
      "keywords": [
        "api",
        "docs",
        "md",
        "response",
        "rules",
        "shape",
        "standards",
        "amount",
        "created",
        "false",
        "items",
        "json",
        "next",
        "null",
        "page",
        "pagination",
        "size",
        "total",
        "反例",
        "正例"
      ],
      "relations": {
        "capabilities": [
          "api",
          "docs",
          "response",
          "rules",
          "shape",
          "standards"
        ],
        "framework": null,
        "kind": "standard",
        "language": "docs",
        "service": null
      },
      "source_path": "docs/standards/rules/api-response-shape.md",
      "start_line": 22,
      "summary": "示例 in docs/standards/rules/api-response-shape.md"
    },
    {
      "chunk_id": "docs.standards.rules.api-response-shape#chunk-006",
      "end_line": 54,
      "heading": "检查清单",
      "keywords": [
        "api",
        "docs",
        "md",
        "response",
        "rules",
        "shape",
        "standards",
        "检查清单",
        "一端点的",
        "且没有对",
        "功响应顶",
        "同一端点",
        "响应顶层",
        "对象和数",
        "层结构是",
        "应顶层结",
        "成功响应",
        "是否稳定",
        "有对象和",
        "构是否稳"
      ],
      "relations": {
        "capabilities": [
          "api",
          "docs",
          "response",
          "rules",
          "shape",
          "standards"
        ],
        "framework": null,
        "kind": "standard",
        "language": "docs",
        "service": null
      },
      "source_path": "docs/standards/rules/api-response-shape.md",
      "start_line": 47,
      "summary": "检查清单 in docs/standards/rules/api-response-shape.md"
    },
    {
      "chunk_id": "docs.standards.rules.api-response-shape#chunk-007",
      "end_line": 61,
      "heading": "相关规范",
      "keywords": [
        "api",
        "docs",
        "md",
        "response",
        "rules",
        "shape",
        "standards",
        "相关规范",
        "data",
        "decisions",
        "design",
        "error",
        "formats",
        "null",
        "rest"
      ],
      "relations": {
        "capabilities": [
          "api",
          "docs",
          "response",
          "rules",
          "shape",
          "standards"
        ],
        "framework": null,
        "kind": "standard",
        "language": "docs",
        "service": null
      },
      "source_path": "docs/standards/rules/api-response-shape.md",
      "start_line": 55,
      "summary": "相关规范 in docs/standards/rules/api-response-shape.md"
    },
    {
      "chunk_id": "docs.standards.rules.api-response-shape#chunk-008",
      "end_line": 67,
      "heading": "变更记录",
      "keywords": [
        "api",
        "docs",
        "md",
        "response",
        "rules",
        "shape",
        "standards",
        "变更记录",
        "null",
        "一响应结",
        "充执行级",
        "单和相关",
        "和相关规",
        "建立统一",
        "执行级规",
        "日期",
        "查清单和",
        "检查清单",
        "清单和相",
        "版本"
      ],
      "relations": {
        "capabilities": [
          "api",
          "docs",
          "response",
          "rules",
          "shape",
          "standards"
        ],
        "framework": null,
        "kind": "standard",
        "language": "docs",
        "service": null
      },
      "source_path": "docs/standards/rules/api-response-shape.md",
      "start_line": 62,
      "summary": "变更记录 in docs/standards/rules/api-response-shape.md"
    },
    {
      "chunk_id": "docs.standards.rules.api-rest-design#chunk-001",
      "end_line": 2,
      "heading": "REST API 设计规范",
      "keywords": [
        "api",
        "design",
        "docs",
        "md",
        "rest",
        "rules",
        "standards",
        "设计规范"
      ],
      "relations": {
        "capabilities": [
          "api",
          "design",
          "docs",
          "rest",
          "rules",
          "standards"
        ],
        "framework": null,
        "kind": "standard",
        "language": "docs",
        "service": null
      },
      "source_path": "docs/standards/rules/api-rest-design.md",
      "start_line": 1,
      "summary": "REST API 设计规范 in docs/standards/rules/api-rest-design.md"
    },
    {
      "chunk_id": "docs.standards.rules.api-rest-design#chunk-002",
      "end_line": 6,
      "heading": "目标",
      "keywords": [
        "api",
        "design",
        "docs",
        "md",
        "rest",
        "rules",
        "standards",
        "http",
        "义不一致",
        "于降低资",
        "低资源命",
        "命名混乱",
        "方法语义",
        "法语义不",
        "源命名混",
        "版本演进",
        "用于降低",
        "目标",
        "范用于降",
        "规范用于"
      ],
      "relations": {
        "capabilities": [
          "api",
          "design",
          "docs",
          "rest",
          "rules",
          "standards"
        ],
        "framework": null,
        "kind": "standard",
        "language": "docs",
        "service": null
      },
      "source_path": "docs/standards/rules/api-rest-design.md",
      "start_line": 3,
      "summary": "目标 in docs/standards/rules/api-rest-design.md"
    },
    {
      "chunk_id": "docs.standards.rules.api-rest-design#chunk-003",
      "end_line": 10,
      "heading": "适用范围",
      "keywords": [
        "api",
        "design",
        "docs",
        "md",
        "rest",
        "rules",
        "standards",
        "适用范围",
        "apps",
        "backend",
        "frontend",
        "http",
        "json",
        "mobile",
        "mock",
        "open",
        "rpc",
        "sdk",
        "services",
        "src"
      ],
      "relations": {
        "capabilities": [
          "api",
          "design",
          "docs",
          "rest",
          "rules",
          "standards"
        ],
        "framework": null,
        "kind": "standard",
        "language": "docs",
        "service": null
      },
      "source_path": "docs/standards/rules/api-rest-design.md",
      "start_line": 7,
      "summary": "适用范围 in docs/standards/rules/api-rest-design.md"
    },
    {
      "chunk_id": "docs.standards.rules.api-rest-design#chunk-004",
      "end_line": 21,
      "heading": "规则",
      "keywords": [
        "api",
        "design",
        "docs",
        "md",
        "rest",
        "rules",
        "standards",
        "create",
        "get",
        "order",
        "rpc",
        "业务资源",
        "使用名词",
        "名词复数",
        "和稳定标",
        "复数和稳",
        "径必须表",
        "必须表达",
        "数和稳定",
        "用名词复"
      ],
      "relations": {
        "capabilities": [
          "api",
          "design",
          "docs",
          "rest",
          "rules",
          "standards"
        ],
        "framework": null,
        "kind": "standard",
        "language": "docs",
        "service": null
      },
      "source_path": "docs/standards/rules/api-rest-design.md",
      "start_line": 11,
      "summary": "规则 in docs/standards/rules/api-rest-design.md"
    },
    {
      "chunk_id": "docs.standards.rules.api-rest-design#chunk-005",
      "end_line": 25,
      "heading": "资源",
      "keywords": [
        "api",
        "design",
        "docs",
        "md",
        "rest",
        "rules",
        "standards",
        "不是内部",
        "业务资源",
        "使用名词",
        "内部表名",
        "务资源而",
        "名或方法",
        "名词复数",
        "径使用名",
        "是内部表",
        "源而不是",
        "源路径使",
        "用名词复",
        "类名或方"
      ],
      "relations": {
        "capabilities": [
          "api",
          "design",
          "docs",
          "rest",
          "rules",
          "standards"
        ],
        "framework": null,
        "kind": "standard",
        "language": "docs",
        "service": null
      },
      "source_path": "docs/standards/rules/api-rest-design.md",
      "start_line": 22,
      "summary": "资源 in docs/standards/rules/api-rest-design.md"
    },
    {
      "chunk_id": "docs.standards.rules.api-rest-design#chunk-006",
      "end_line": 29,
      "heading": "方法",
      "keywords": [
        "api",
        "design",
        "docs",
        "md",
        "rest",
        "rules",
        "standards",
        "delete",
        "get",
        "patch",
        "post",
        "put",
        "不得产生",
        "业务副作",
        "于创建资",
        "产生业务",
        "创建资源",
        "务副作用",
        "只能读取",
        "建资源或"
      ],
      "relations": {
        "capabilities": [
          "api",
          "design",
          "docs",
          "rest",
          "rules",
          "standards"
        ],
        "framework": null,
        "kind": "standard",
        "language": "docs",
        "service": null
      },
      "source_path": "docs/standards/rules/api-rest-design.md",
      "start_line": 26,
      "summary": "方法 in docs/standards/rules/api-rest-design.md"
    },
    {
      "chunk_id": "docs.standards.rules.api-rest-design#chunk-007",
      "end_line": 33,
      "heading": "版本",
      "keywords": [
        "api",
        "design",
        "docs",
        "md",
        "rest",
        "rules",
        "standards",
        "入新版本",
        "兼容新增",
        "协商机制",
        "变更必须",
        "坏性变更",
        "容新增字",
        "引入新版",
        "径或协商",
        "必须引入",
        "性变更必",
        "或协商机",
        "新增字段",
        "新版本路"
      ],
      "relations": {
        "capabilities": [
          "api",
          "design",
          "docs",
          "rest",
          "rules",
          "standards"
        ],
        "framework": null,
        "kind": "standard",
        "language": "docs",
        "service": null
      },
      "source_path": "docs/standards/rules/api-rest-design.md",
      "start_line": 30,
      "summary": "版本 in docs/standards/rules/api-rest-design.md"
    },
    {
      "chunk_id": "docs.standards.rules.api-rest-design#chunk-008",
      "end_line": 47,
      "heading": "示例",
      "keywords": [
        "api",
        "design",
        "docs",
        "md",
        "rest",
        "rules",
        "standards",
        "get",
        "http",
        "hzy8",
        "ord",
        "order",
        "orders",
        "post",
        "反例",
        "正例",
        "示例"
      ],
      "relations": {
        "capabilities": [
          "api",
          "design",
          "docs",
          "rest",
          "rules",
          "standards"
        ],
        "framework": null,
        "kind": "standard",
        "language": "docs",
        "service": null
      },
      "source_path": "docs/standards/rules/api-rest-design.md",
      "start_line": 34,
      "summary": "示例 in docs/standards/rules/api-rest-design.md"
    },
    {
      "chunk_id": "docs.standards.rules.api-rest-design#chunk-009",
      "end_line": 55,
      "heading": "检查清单",
      "keywords": [
        "api",
        "design",
        "docs",
        "md",
        "rest",
        "rules",
        "standards",
        "检查清单",
        "http",
        "rpc",
        "且没有动",
        "业务资源",
        "否表达稳",
        "命名",
        "定业务资",
        "幂等性",
        "径是否表",
        "态码和重",
        "方法",
        "是否表达"
      ],
      "relations": {
        "capabilities": [
          "api",
          "design",
          "docs",
          "rest",
          "rules",
          "standards"
        ],
        "framework": null,
        "kind": "standard",
        "language": "docs",
        "service": null
      },
      "source_path": "docs/standards/rules/api-rest-design.md",
      "start_line": 48,
      "summary": "检查清单 in docs/standards/rules/api-rest-design.md"
    },
    {
      "chunk_id": "docs.standards.rules.api-rest-design#chunk-010",
      "end_line": 63,
      "heading": "相关规范",
      "keywords": [
        "api",
        "design",
        "docs",
        "md",
        "rest",
        "rules",
        "standards",
        "相关规范",
        "data",
        "formats",
        "http",
        "idempotency",
        "input",
        "references",
        "response",
        "shape",
        "status",
        "validation"
      ],
      "relations": {
        "capabilities": [
          "api",
          "design",
          "docs",
          "rest",
          "rules",
          "standards"
        ],
        "framework": null,
        "kind": "standard",
        "language": "docs",
        "service": null
      },
      "source_path": "docs/standards/rules/api-rest-design.md",
      "start_line": 56,
      "summary": "相关规范 in docs/standards/rules/api-rest-design.md"
    }
  ],
  "schema_version": "1.0.0"
}
