{
  "chunks": [
    {
      "chunk_id": "docs.standards.rules.logging#chunk-001",
      "end_line": 2,
      "heading": "日志规范",
      "keywords": [
        "docs",
        "logging",
        "md",
        "rules",
        "standards",
        "日志规范"
      ],
      "relations": {
        "capabilities": [
          "docs",
          "logging",
          "rules",
          "standards"
        ],
        "framework": null,
        "kind": "standard",
        "language": "docs",
        "service": null
      },
      "source_hash": "sha256:df33617b6ef63f74835f7fc9a7fd43eeea54cbc4539aa45ccb731217d119a943",
      "source_path": "docs/standards/rules/logging.md",
      "start_line": 1,
      "summary": "日志规范 in docs/standards/rules/logging.md"
    },
    {
      "chunk_id": "docs.standards.rules.logging#chunk-002",
      "end_line": 6,
      "heading": "目标",
      "keywords": [
        "docs",
        "logging",
        "md",
        "rules",
        "standards",
        "于降低故",
        "低故障排",
        "依赖自由",
        "志级别滥",
        "志规范用",
        "排查依赖",
        "故障排查",
        "敏感数据",
        "日志级别",
        "日志规范",
        "查依赖自",
        "用于降低",
        "目标",
        "级别滥用",
        "自由文本"
      ],
      "relations": {
        "capabilities": [
          "docs",
          "logging",
          "rules",
          "standards"
        ],
        "framework": null,
        "kind": "standard",
        "language": "docs",
        "service": null
      },
      "source_hash": "sha256:df33617b6ef63f74835f7fc9a7fd43eeea54cbc4539aa45ccb731217d119a943",
      "source_path": "docs/standards/rules/logging.md",
      "start_line": 3,
      "summary": "目标 in docs/standards/rules/logging.md"
    },
    {
      "chunk_id": "docs.standards.rules.logging#chunk-003",
      "end_line": 10,
      "heading": "适用范围",
      "keywords": [
        "docs",
        "logging",
        "md",
        "rules",
        "standards",
        "适用范围",
        "api",
        "apps",
        "backend",
        "http",
        "pii",
        "rpc",
        "services",
        "src",
        "trace",
        "后台作业",
        "处理任务",
        "息消费者",
        "批处理任",
        "服务"
      ],
      "relations": {
        "capabilities": [
          "docs",
          "logging",
          "rules",
          "standards"
        ],
        "framework": null,
        "kind": "standard",
        "language": "docs",
        "service": null
      },
      "source_hash": "sha256:df33617b6ef63f74835f7fc9a7fd43eeea54cbc4539aa45ccb731217d119a943",
      "source_path": "docs/standards/rules/logging.md",
      "start_line": 7,
      "summary": "适用范围 in docs/standards/rules/logging.md"
    },
    {
      "chunk_id": "docs.standards.rules.logging#chunk-004",
      "end_line": 21,
      "heading": "规则",
      "keywords": [
        "docs",
        "logging",
        "md",
        "rules",
        "standards",
        "environment",
        "service",
        "trace",
        "version",
        "产日志必",
        "价关联字",
        "使用结构",
        "关联字段",
        "并包含",
        "必须使用",
        "志必须使",
        "或等价关",
        "日志必须",
        "构化格式",
        "生产日志"
      ],
      "relations": {
        "capabilities": [
          "docs",
          "logging",
          "rules",
          "standards"
        ],
        "framework": null,
        "kind": "standard",
        "language": "docs",
        "service": null
      },
      "source_hash": "sha256:df33617b6ef63f74835f7fc9a7fd43eeea54cbc4539aa45ccb731217d119a943",
      "source_path": "docs/standards/rules/logging.md",
      "start_line": 11,
      "summary": "规则 in docs/standards/rules/logging.md"
    },
    {
      "chunk_id": "docs.standards.rules.logging#chunk-005",
      "end_line": 45,
      "heading": "示例",
      "keywords": [
        "docs",
        "logging",
        "md",
        "rules",
        "standards",
        "api",
        "code",
        "create",
        "customer",
        "environment",
        "error",
        "f9c2d8e7a6b4c10",
        "json",
        "level",
        "operation",
        "order",
        "payment",
        "prod",
        "service",
        "timeout"
      ],
      "relations": {
        "capabilities": [
          "docs",
          "logging",
          "rules",
          "standards"
        ],
        "framework": null,
        "kind": "standard",
        "language": "docs",
        "service": null
      },
      "source_hash": "sha256:df33617b6ef63f74835f7fc9a7fd43eeea54cbc4539aa45ccb731217d119a943",
      "source_path": "docs/standards/rules/logging.md",
      "start_line": 22,
      "summary": "示例 in docs/standards/rules/logging.md"
    },
    {
      "chunk_id": "docs.standards.rules.logging#chunk-006",
      "end_line": 54,
      "heading": "检查清单",
      "keywords": [
        "docs",
        "logging",
        "md",
        "rules",
        "standards",
        "检查清单",
        "trace",
        "为结构化",
        "关联信息",
        "包含服务",
        "包含稳定",
        "否为结构",
        "否包含稳",
        "并包含服",
        "志是否为",
        "志是否包",
        "日志是否",
        "是否为结",
        "是否包含",
        "构化字段"
      ],
      "relations": {
        "capabilities": [
          "docs",
          "logging",
          "rules",
          "standards"
        ],
        "framework": null,
        "kind": "standard",
        "language": "docs",
        "service": null
      },
      "source_hash": "sha256:df33617b6ef63f74835f7fc9a7fd43eeea54cbc4539aa45ccb731217d119a943",
      "source_path": "docs/standards/rules/logging.md",
      "start_line": 46,
      "summary": "检查清单 in docs/standards/rules/logging.md"
    },
    {
      "chunk_id": "docs.standards.rules.logging#chunk-007",
      "end_line": 61,
      "heading": "相关规范",
      "keywords": [
        "docs",
        "logging",
        "md",
        "rules",
        "standards",
        "相关规范",
        "error",
        "handling",
        "metrics",
        "pii",
        "tracing"
      ],
      "relations": {
        "capabilities": [
          "docs",
          "logging",
          "rules",
          "standards"
        ],
        "framework": null,
        "kind": "standard",
        "language": "docs",
        "service": null
      },
      "source_hash": "sha256:df33617b6ef63f74835f7fc9a7fd43eeea54cbc4539aa45ccb731217d119a943",
      "source_path": "docs/standards/rules/logging.md",
      "start_line": 55,
      "summary": "相关规范 in docs/standards/rules/logging.md"
    },
    {
      "chunk_id": "docs.standards.rules.logging#chunk-008",
      "end_line": 67,
      "heading": "变更记录",
      "keywords": [
        "docs",
        "logging",
        "md",
        "rules",
        "standards",
        "变更记录",
        "充执行级",
        "初始规范",
        "单和相关",
        "和相关规",
        "建立初始",
        "执行级规",
        "日期",
        "查清单和",
        "检查清单",
        "清单和相",
        "版本",
        "相关规范",
        "示例",
        "立初始规"
      ],
      "relations": {
        "capabilities": [
          "docs",
          "logging",
          "rules",
          "standards"
        ],
        "framework": null,
        "kind": "standard",
        "language": "docs",
        "service": null
      },
      "source_hash": "sha256:df33617b6ef63f74835f7fc9a7fd43eeea54cbc4539aa45ccb731217d119a943",
      "source_path": "docs/standards/rules/logging.md",
      "start_line": 62,
      "summary": "变更记录 in docs/standards/rules/logging.md"
    }
  ],
  "schema_version": "1.0.0",
  "source_path": "docs/standards/rules/logging.md"
}
