{
  "chunks": [
    {
      "chunk_id": "backend.dotnet.Services.Notice.README#chunk-001",
      "end_line": 3,
      "heading": "通知服务目录",
      "keywords": [
        "backend",
        "dotnet",
        "md",
        "notice",
        "readme",
        "services",
        "通知服务目录",
        "于承载站",
        "和通知测",
        "录用于承",
        "承载站内",
        "服务目录",
        "本目录用",
        "板和通知",
        "模板和通",
        "测试相关",
        "消息触达",
        "用于承载",
        "目录用于",
        "知服务目"
      ],
      "relations": {
        "capabilities": [
          "backend",
          "dotnet",
          "notice",
          "services"
        ],
        "framework": null,
        "kind": "readme",
        "language": "dotnet",
        "service": "notice"
      },
      "source_path": "backend/dotnet/Services/Notice/README.md",
      "start_line": 1,
      "summary": "通知服务目录 in backend/dotnet/Services/Notice/README.md"
    }
  ],
  "schema_version": "1.0.0"
}
