{
  "chunks": [
    {
      "chunk_id": "README#chunk-001",
      "end_line": 3,
      "heading": "Tw.SmartPlatform",
      "keywords": [
        "md",
        "readme",
        "smartplatform",
        "platform",
        "smart",
        "于组织后",
        "前端",
        "向企业端",
        "契约",
        "录用于组",
        "慧管理系",
        "是面向企",
        "智慧管理",
        "构的智慧",
        "架构的智",
        "根目录用",
        "用于组织",
        "的智慧管",
        "目录用于",
        "管理系统"
      ],
      "relations": {
        "capabilities": [],
        "framework": null,
        "kind": "readme",
        "language": null,
        "service": null
      },
      "source_path": "README.md",
      "start_line": 1,
      "summary": "Tw.SmartPlatform in README.md"
    },
    {
      "chunk_id": "backend.README#chunk-001",
      "end_line": 3,
      "heading": "后端目录",
      "keywords": [
        "backend",
        "md",
        "readme",
        "后端目录",
        "java",
        "net",
        "python",
        "中存放后",
        "于集中存",
        "后端相关",
        "存放后端",
        "并按",
        "录用于集",
        "技术栈组",
        "放后端相",
        "本目录用",
        "术栈组织",
        "栈组织服",
        "用于集中",
        "目录用于"
      ],
      "relations": {
        "capabilities": [
          "backend"
        ],
        "framework": null,
        "kind": "readme",
        "language": null,
        "service": null
      },
      "source_path": "backend/README.md",
      "start_line": 1,
      "summary": "后端目录 in backend/README.md"
    },
    {
      "chunk_id": "backend.dotnet.Aspire.README#chunk-001",
      "end_line": 3,
      "heading": ".NET Aspire 编排目录",
      "keywords": [
        "aspire",
        "backend",
        "dotnet",
        "md",
        "net",
        "readme",
        "编排目录",
        "关的本地",
        "务启动和",
        "动和运行",
        "启动和运",
        "和运行时",
        "地开发编",
        "开发编排",
        "录用于存",
        "服务启动",
        "本地开发",
        "本目录用",
        "用于存放",
        "的本地开"
      ],
      "relations": {
        "capabilities": [
          "aspire",
          "backend",
          "dotnet"
        ],
        "framework": null,
        "kind": "readme",
        "language": "dotnet",
        "service": null
      },
      "source_path": "backend/dotnet/Aspire/README.md",
      "start_line": 1,
      "summary": ".NET Aspire 编排目录 in backend/dotnet/Aspire/README.md"
    },
    {
      "chunk_id": "backend.dotnet.BuildingBlocks.README#chunk-001",
      "end_line": 3,
      "heading": ".NET 公共构件目录",
      "keywords": [
        "backend",
        "buildingblocks",
        "dotnet",
        "md",
        "net",
        "readme",
        "公共构件目录",
        "公共构件",
        "共构件目",
        "分层组件",
        "动分层组",
        "可复用的",
        "后端可复",
        "域驱动分",
        "复用的基",
        "层组件和",
        "录用于存",
        "本目录用",
        "构件目录",
        "用于存放"
      ],
      "relations": {
        "capabilities": [
          "backend",
          "buildingblocks",
          "dotnet"
        ],
        "framework": null,
        "kind": "readme",
        "language": "dotnet",
        "service": null
      },
      "source_path": "backend/dotnet/BuildingBlocks/README.md",
      "start_line": 1,
      "summary": ".NET 公共构件目录 in backend/dotnet/BuildingBlocks/README.md"
    },
    {
      "chunk_id": "backend.dotnet.BuildingBlocks.src.Ddd.Tw.Application.Contracts.README#chunk-001",
      "end_line": 3,
      "heading": "应用契约构件目录",
      "keywords": [
        "application",
        "backend",
        "buildingblocks",
        "contracts",
        "ddd",
        "dotnet",
        "md",
        "readme",
        "src",
        "tw",
        "应用契约构件目录",
        "于承载应",
        "务对外暴",
        "外暴露的",
        "契约构件",
        "对外暴露",
        "应用契约",
        "应用服务",
        "录用于承",
        "承载应用"
      ],
      "relations": {
        "capabilities": [
          "application",
          "backend",
          "buildingblocks",
          "contracts",
          "ddd",
          "dotnet",
          "src"
        ],
        "framework": "ddd",
        "kind": "readme",
        "language": "dotnet",
        "service": null
      },
      "source_path": "backend/dotnet/BuildingBlocks/src/Ddd/Tw.Application.Contracts/README.md",
      "start_line": 1,
      "summary": "应用契约构件目录 in backend/dotnet/BuildingBlocks/src/Ddd/Tw.Application.Contracts/README.md"
    },
    {
      "chunk_id": "backend.dotnet.BuildingBlocks.src.Ddd.Tw.Application.README#chunk-001",
      "end_line": 3,
      "heading": "应用层构件目录",
      "keywords": [
        "application",
        "backend",
        "buildingblocks",
        "ddd",
        "dotnet",
        "md",
        "readme",
        "src",
        "tw",
        "应用层构件目录",
        "事务边界",
        "于承载应",
        "务边界和",
        "和应用层",
        "层构件目",
        "应用层构",
        "应用服务",
        "录用于承",
        "承载应用",
        "服务实现"
      ],
      "relations": {
        "capabilities": [
          "application",
          "backend",
          "buildingblocks",
          "ddd",
          "dotnet",
          "src"
        ],
        "framework": "ddd",
        "kind": "readme",
        "language": "dotnet",
        "service": null
      },
      "source_path": "backend/dotnet/BuildingBlocks/src/Ddd/Tw.Application/README.md",
      "start_line": 1,
      "summary": "应用层构件目录 in backend/dotnet/BuildingBlocks/src/Ddd/Tw.Application/README.md"
    },
    {
      "chunk_id": "backend.dotnet.BuildingBlocks.src.Ddd.Tw.Domain.README#chunk-001",
      "end_line": 3,
      "heading": "领域层构件目录",
      "keywords": [
        "backend",
        "buildingblocks",
        "ddd",
        "domain",
        "dotnet",
        "md",
        "readme",
        "src",
        "tw",
        "领域层构件目录",
        "中的实体",
        "于承载领",
        "动设计中",
        "域层构件",
        "域驱动设",
        "层构件目",
        "录用于承",
        "承载领域",
        "本目录用",
        "构件目录"
      ],
      "relations": {
        "capabilities": [
          "backend",
          "buildingblocks",
          "ddd",
          "domain",
          "dotnet",
          "src"
        ],
        "framework": "ddd",
        "kind": "readme",
        "language": "dotnet",
        "service": null
      },
      "source_path": "backend/dotnet/BuildingBlocks/src/Ddd/Tw.Domain/README.md",
      "start_line": 1,
      "summary": "领域层构件目录 in backend/dotnet/BuildingBlocks/src/Ddd/Tw.Domain/README.md"
    },
    {
      "chunk_id": "backend.dotnet.BuildingBlocks.src.Ddd.Tw.Domain.Shared.README#chunk-001",
      "end_line": 3,
      "heading": "共享领域构件目录",
      "keywords": [
        "backend",
        "buildingblocks",
        "ddd",
        "domain",
        "dotnet",
        "md",
        "readme",
        "shared",
        "src",
        "tw",
        "共享领域构件目录",
        "与应用层",
        "于承载领",
        "享领域构",
        "共享领域",
        "共同使用",
        "域层与应",
        "域构件目",
        "层与应用",
        "层共同使"
      ],
      "relations": {
        "capabilities": [
          "backend",
          "buildingblocks",
          "ddd",
          "domain",
          "dotnet",
          "shared",
          "src"
        ],
        "framework": "ddd",
        "kind": "readme",
        "language": "dotnet",
        "service": null
      },
      "source_path": "backend/dotnet/BuildingBlocks/src/Ddd/Tw.Domain.Shared/README.md",
      "start_line": 1,
      "summary": "共享领域构件目录 in backend/dotnet/BuildingBlocks/src/Ddd/Tw.Domain.Shared/README.md"
    },
    {
      "chunk_id": "backend.dotnet.BuildingBlocks.src.Tw.AspNetCore.README#chunk-001",
      "end_line": 3,
      "heading": "ASP.NET Core 集成构件目录",
      "keywords": [
        "asp",
        "aspnetcore",
        "backend",
        "buildingblocks",
        "core",
        "dotnet",
        "md",
        "net",
        "readme",
        "src",
        "tw",
        "集成构件目录",
        "web",
        "中间件",
        "和通用启",
        "基础集成",
        "展和通用",
        "应用的基",
        "录用于承",
        "成构件目"
      ],
      "relations": {
        "capabilities": [
          "aspnetcore",
          "backend",
          "buildingblocks",
          "dotnet",
          "src"
        ],
        "framework": "tw.aspnetcore",
        "kind": "readme",
        "language": "dotnet",
        "service": null
      },
      "source_path": "backend/dotnet/BuildingBlocks/src/Tw.AspNetCore/README.md",
      "start_line": 1,
      "summary": "ASP.NET Core 集成构件目录 in backend/dotnet/BuildingBlocks/src/Tw.AspNetCore/README.md"
    },
    {
      "chunk_id": "backend.dotnet.BuildingBlocks.src.Tw.Caching.README#chunk-001",
      "end_line": 3,
      "heading": "缓存构件目录",
      "keywords": [
        "backend",
        "buildingblocks",
        "caching",
        "dotnet",
        "md",
        "readme",
        "src",
        "tw",
        "缓存构件目录",
        "于承载缓",
        "供者集成",
        "和通用缓",
        "存提供者",
        "存构件目",
        "录用于承",
        "成和通用",
        "承载缓存",
        "提供者集",
        "本目录用",
        "构件目录"
      ],
      "relations": {
        "capabilities": [
          "backend",
          "buildingblocks",
          "caching",
          "dotnet",
          "src"
        ],
        "framework": "tw.caching",
        "kind": "readme",
        "language": "dotnet",
        "service": null
      },
      "source_path": "backend/dotnet/BuildingBlocks/src/Tw.Caching/README.md",
      "start_line": 1,
      "summary": "缓存构件目录 in backend/dotnet/BuildingBlocks/src/Tw.Caching/README.md"
    },
    {
      "chunk_id": "backend.dotnet.BuildingBlocks.src.Tw.Core.README#chunk-001",
      "end_line": 3,
      "heading": "核心基础构件目录",
      "keywords": [
        "backend",
        "buildingblocks",
        "core",
        "dotnet",
        "md",
        "readme",
        "src",
        "tw",
        "核心基础构件目录",
        "于承载后",
        "后端通用",
        "基础工具",
        "基础构件",
        "录用于承",
        "心基础构",
        "扩展方法",
        "承载后端",
        "本目录用",
        "构件目录",
        "核心基础"
      ],
      "relations": {
        "capabilities": [
          "backend",
          "buildingblocks",
          "core",
          "dotnet",
          "src"
        ],
        "framework": "tw.core",
        "kind": "readme",
        "language": "dotnet",
        "service": null
      },
      "source_path": "backend/dotnet/BuildingBlocks/src/Tw.Core/README.md",
      "start_line": 1,
      "summary": "核心基础构件目录 in backend/dotnet/BuildingBlocks/src/Tw.Core/README.md"
    },
    {
      "chunk_id": "backend.dotnet.BuildingBlocks.src.Tw.DistributedLocking.README#chunk-001",
      "end_line": 3,
      "heading": "分布式锁构件目录",
      "keywords": [
        "backend",
        "buildingblocks",
        "distributedlocking",
        "dotnet",
        "md",
        "readme",
        "src",
        "tw",
        "分布式锁构件目录",
        "于承载分",
        "分布式锁",
        "制和跨实",
        "发控制和",
        "和跨实例",
        "布式锁抽",
        "布式锁构",
        "并发控制",
        "式锁抽象",
        "式锁构件",
        "录用于承"
      ],
      "relations": {
        "capabilities": [
          "backend",
          "buildingblocks",
          "distributedlocking",
          "dotnet",
          "src"
        ],
        "framework": "tw.distributedlocking",
        "kind": "readme",
        "language": "dotnet",
        "service": null
      },
      "source_path": "backend/dotnet/BuildingBlocks/src/Tw.DistributedLocking/README.md",
      "start_line": 1,
      "summary": "分布式锁构件目录 in backend/dotnet/BuildingBlocks/src/Tw.DistributedLocking/README.md"
    },
    {
      "chunk_id": "backend.dotnet.BuildingBlocks.src.Tw.DocumentProcessing.README#chunk-001",
      "end_line": 3,
      "heading": "文档处理构件目录",
      "keywords": [
        "backend",
        "buildingblocks",
        "documentprocessing",
        "dotnet",
        "md",
        "readme",
        "src",
        "tw",
        "文档处理构件目录",
        "于承载文",
        "和处理流",
        "处理构件",
        "处理流程",
        "录用于承",
        "承载文档",
        "换和处理",
        "文档处理",
        "文档生成",
        "本目录用",
        "构件目录"
      ],
      "relations": {
        "capabilities": [
          "backend",
          "buildingblocks",
          "documentprocessing",
          "dotnet",
          "src"
        ],
        "framework": "tw.documentprocessing",
        "kind": "readme",
        "language": "dotnet",
        "service": null
      },
      "source_path": "backend/dotnet/BuildingBlocks/src/Tw.DocumentProcessing/README.md",
      "start_line": 1,
      "summary": "文档处理构件目录 in backend/dotnet/BuildingBlocks/src/Tw.DocumentProcessing/README.md"
    },
    {
      "chunk_id": "backend.dotnet.BuildingBlocks.src.Tw.EventBus.README#chunk-001",
      "end_line": 3,
      "heading": "事件总线构件目录",
      "keywords": [
        "backend",
        "buildingblocks",
        "dotnet",
        "eventbus",
        "md",
        "readme",
        "src",
        "tw",
        "事件总线构件目录",
        "事件发布",
        "事件总线",
        "事件转发",
        "于承载事",
        "件发布订",
        "件总线构",
        "件转发和",
        "发布订阅",
        "域事件转",
        "录用于承",
        "总线构件"
      ],
      "relations": {
        "capabilities": [
          "backend",
          "buildingblocks",
          "dotnet",
          "eventbus",
          "src"
        ],
        "framework": "tw.eventbus",
        "kind": "readme",
        "language": "dotnet",
        "service": null
      },
      "source_path": "backend/dotnet/BuildingBlocks/src/Tw.EventBus/README.md",
      "start_line": 1,
      "summary": "事件总线构件目录 in backend/dotnet/BuildingBlocks/src/Tw.EventBus/README.md"
    },
    {
      "chunk_id": "backend.dotnet.BuildingBlocks.src.Tw.MultiTenancy.README#chunk-001",
      "end_line": 3,
      "heading": "多租户构件目录",
      "keywords": [
        "backend",
        "buildingblocks",
        "dotnet",
        "md",
        "multitenancy",
        "readme",
        "src",
        "tw",
        "多租户构件目录",
        "于承载多",
        "和租户配",
        "多租户构",
        "多租户识",
        "录用于承",
        "户上下文",
        "户构件目",
        "户隔离和",
        "承载多租",
        "本目录用",
        "构件目录"
      ],
      "relations": {
        "capabilities": [
          "backend",
          "buildingblocks",
          "dotnet",
          "multitenancy",
          "src"
        ],
        "framework": "tw.multitenancy",
        "kind": "readme",
        "language": "dotnet",
        "service": null
      },
      "source_path": "backend/dotnet/BuildingBlocks/src/Tw.MultiTenancy/README.md",
      "start_line": 1,
      "summary": "多租户构件目录 in backend/dotnet/BuildingBlocks/src/Tw.MultiTenancy/README.md"
    },
    {
      "chunk_id": "backend.dotnet.BuildingBlocks.src.Tw.PinYinConverter.README#chunk-001",
      "end_line": 3,
      "heading": "拼音转换构件目录",
      "keywords": [
        "backend",
        "buildingblocks",
        "dotnet",
        "md",
        "pinyinconverter",
        "readme",
        "src",
        "tw",
        "拼音转换构件目录",
        "中文拼音",
        "于承载中",
        "助和文本",
        "和文本规",
        "录用于承",
        "承载中文",
        "拼音转换",
        "换构件目",
        "文拼音转",
        "文本规范",
        "本目录用"
      ],
      "relations": {
        "capabilities": [
          "backend",
          "buildingblocks",
          "dotnet",
          "pinyinconverter",
          "src"
        ],
        "framework": "tw.pinyinconverter",
        "kind": "readme",
        "language": "dotnet",
        "service": null
      },
      "source_path": "backend/dotnet/BuildingBlocks/src/Tw.PinYinConverter/README.md",
      "start_line": 1,
      "summary": "拼音转换构件目录 in backend/dotnet/BuildingBlocks/src/Tw.PinYinConverter/README.md"
    },
    {
      "chunk_id": "backend.dotnet.BuildingBlocks.src.Tw.RemoteService.README#chunk-001",
      "end_line": 3,
      "heading": "远程服务构件目录",
      "keywords": [
        "backend",
        "buildingblocks",
        "dotnet",
        "md",
        "readme",
        "remoteservice",
        "src",
        "tw",
        "远程服务构件目录",
        "于承载远",
        "务构件目",
        "发和服务",
        "口转发和",
        "客户端代",
        "录用于承",
        "户端代理",
        "承载远程",
        "接口转发",
        "服务构件",
        "服务调用"
      ],
      "relations": {
        "capabilities": [
          "backend",
          "buildingblocks",
          "dotnet",
          "remoteservice",
          "src"
        ],
        "framework": "tw.remoteservice",
        "kind": "readme",
        "language": "dotnet",
        "service": null
      },
      "source_path": "backend/dotnet/BuildingBlocks/src/Tw.RemoteService/README.md",
      "start_line": 1,
      "summary": "远程服务构件目录 in backend/dotnet/BuildingBlocks/src/Tw.RemoteService/README.md"
    },
    {
      "chunk_id": "backend.dotnet.BuildingBlocks.src.Tw.SqlSugar.README#chunk-001",
      "end_line": 3,
      "heading": "SqlSugar 数据访问构件目录",
      "keywords": [
        "backend",
        "buildingblocks",
        "dotnet",
        "md",
        "readme",
        "sqlsugar",
        "src",
        "tw",
        "数据访问构件目录",
        "sql",
        "sugar",
        "于承载基",
        "仓储支持",
        "储支持和",
        "录用于承",
        "承载基于",
        "持和数据",
        "据访问封",
        "据访问构",
        "支持和数"
      ],
      "relations": {
        "capabilities": [
          "backend",
          "buildingblocks",
          "dotnet",
          "sqlsugar",
          "src"
        ],
        "framework": "tw.sqlsugar",
        "kind": "readme",
        "language": "dotnet",
        "service": null
      },
      "source_path": "backend/dotnet/BuildingBlocks/src/Tw.SqlSugar/README.md",
      "start_line": 1,
      "summary": "SqlSugar 数据访问构件目录 in backend/dotnet/BuildingBlocks/src/Tw.SqlSugar/README.md"
    },
    {
      "chunk_id": "backend.dotnet.BuildingBlocks.src.Tw.TextTemplating.README#chunk-001",
      "end_line": 3,
      "heading": "文本模板构件目录",
      "keywords": [
        "backend",
        "buildingblocks",
        "dotnet",
        "md",
        "readme",
        "src",
        "texttemplating",
        "tw",
        "文本模板构件目录",
        "于承载文",
        "变量替换",
        "和模板化",
        "录用于承",
        "承载文本",
        "换和模板",
        "文本模板",
        "替换和模",
        "本模板构",
        "本模板渲",
        "本目录用"
      ],
      "relations": {
        "capabilities": [
          "backend",
          "buildingblocks",
          "dotnet",
          "src",
          "texttemplating"
        ],
        "framework": "tw.texttemplating",
        "kind": "readme",
        "language": "dotnet",
        "service": null
      },
      "source_path": "backend/dotnet/BuildingBlocks/src/Tw.TextTemplating/README.md",
      "start_line": 1,
      "summary": "文本模板构件目录 in backend/dotnet/BuildingBlocks/src/Tw.TextTemplating/README.md"
    },
    {
      "chunk_id": "backend.dotnet.BuildingBlocks.src.Tw.Uow.README#chunk-001",
      "end_line": 3,
      "heading": "工作单元构件目录",
      "keywords": [
        "backend",
        "buildingblocks",
        "dotnet",
        "md",
        "readme",
        "src",
        "tw",
        "uow",
        "工作单元构件目录",
        "于承载工",
        "作单元构",
        "作单元模",
        "元构件目",
        "元模式相",
        "关的事务",
        "单元构件",
        "单元模式",
        "工作单元",
        "式相关的",
        "录用于承"
      ],
      "relations": {
        "capabilities": [
          "backend",
          "buildingblocks",
          "dotnet",
          "src",
          "uow"
        ],
        "framework": "tw.uow",
        "kind": "readme",
        "language": "dotnet",
        "service": null
      },
      "source_path": "backend/dotnet/BuildingBlocks/src/Tw.Uow/README.md",
      "start_line": 1,
      "summary": "工作单元构件目录 in backend/dotnet/BuildingBlocks/src/Tw.Uow/README.md"
    },
    {
      "chunk_id": "backend.dotnet.README#chunk-001",
      "end_line": 3,
      "heading": ".NET 后端目录",
      "keywords": [
        "backend",
        "dotnet",
        "md",
        "net",
        "readme",
        "后端目录",
        "一构建配",
        "业务服务",
        "件和统一",
        "公共构件",
        "共构件和",
        "后端解决",
        "和统一构",
        "录用于承",
        "本目录用",
        "构件和统",
        "构建配置",
        "用于承载",
        "目录用于",
        "端解决方"
      ],
      "relations": {
        "capabilities": [
          "backend",
          "dotnet"
        ],
        "framework": null,
        "kind": "readme",
        "language": "dotnet",
        "service": null
      },
      "source_path": "backend/dotnet/README.md",
      "start_line": 1,
      "summary": ".NET 后端目录 in backend/dotnet/README.md"
    },
    {
      "chunk_id": "backend.dotnet.Services.Authentication.README#chunk-001",
      "end_line": 3,
      "heading": "认证服务目录",
      "keywords": [
        "authentication",
        "backend",
        "dotnet",
        "md",
        "readme",
        "services",
        "认证服务目录",
        "于承载用",
        "令牌签发",
        "发和认证",
        "和认证测",
        "录用于承",
        "户身份认",
        "承载用户",
        "服务目录",
        "本目录用",
        "牌签发和",
        "用于承载",
        "用户身份",
        "登录流程"
      ],
      "relations": {
        "capabilities": [
          "authentication",
          "backend",
          "dotnet",
          "services"
        ],
        "framework": null,
        "kind": "readme",
        "language": "dotnet",
        "service": "authentication"
      },
      "source_path": "backend/dotnet/Services/Authentication/README.md",
      "start_line": 1,
      "summary": "认证服务目录 in backend/dotnet/Services/Authentication/README.md"
    },
    {
      "chunk_id": "backend.dotnet.Services.Authorization.README#chunk-001",
      "end_line": 3,
      "heading": "授权服务目录",
      "keywords": [
        "authorization",
        "backend",
        "dotnet",
        "md",
        "readme",
        "services",
        "授权服务目录",
        "于承载权",
        "和授权测",
        "录用于承",
        "承载权限",
        "授权和授",
        "授权服务",
        "授权测试",
        "服务目录",
        "本目录用",
        "权和授权",
        "权服务目",
        "权测试相",
        "权限校验"
      ],
      "relations": {
        "capabilities": [
          "authorization",
          "backend",
          "dotnet",
          "services"
        ],
        "framework": null,
        "kind": "readme",
        "language": "dotnet",
        "service": "authorization"
      },
      "source_path": "backend/dotnet/Services/Authorization/README.md",
      "start_line": 1,
      "summary": "授权服务目录 in backend/dotnet/Services/Authorization/README.md"
    },
    {
      "chunk_id": "backend.dotnet.Services.Notice.README#chunk-001",
      "end_line": 3,
      "heading": "通知服务目录",
      "keywords": [
        "backend",
        "dotnet",
        "md",
        "notice",
        "readme",
        "services",
        "通知服务目录",
        "于承载站",
        "和通知测",
        "录用于承",
        "承载站内",
        "服务目录",
        "本目录用",
        "板和通知",
        "模板和通",
        "测试相关",
        "消息触达",
        "用于承载",
        "目录用于",
        "知服务目"
      ],
      "relations": {
        "capabilities": [
          "backend",
          "dotnet",
          "notice",
          "services"
        ],
        "framework": null,
        "kind": "readme",
        "language": "dotnet",
        "service": "notice"
      },
      "source_path": "backend/dotnet/Services/Notice/README.md",
      "start_line": 1,
      "summary": "通知服务目录 in backend/dotnet/Services/Notice/README.md"
    },
    {
      "chunk_id": "backend.dotnet.Services.OSS.README#chunk-001",
      "end_line": 3,
      "heading": "对象存储服务目录",
      "keywords": [
        "backend",
        "dotnet",
        "md",
        "oss",
        "readme",
        "services",
        "对象存储服务目录",
        "上传下载",
        "于承载对",
        "件上传下",
        "储服务目",
        "和存储测",
        "存储服务",
        "对象存储",
        "录用于承",
        "承载对象",
        "文件上传",
        "服务目录",
        "本目录用",
        "源访问和"
      ],
      "relations": {
        "capabilities": [
          "backend",
          "dotnet",
          "oss",
          "services"
        ],
        "framework": null,
        "kind": "readme",
        "language": "dotnet",
        "service": "oss"
      },
      "source_path": "backend/dotnet/Services/OSS/README.md",
      "start_line": 1,
      "summary": "对象存储服务目录 in backend/dotnet/Services/OSS/README.md"
    },
    {
      "chunk_id": "backend.dotnet.Services.README#chunk-001",
      "end_line": 3,
      "heading": ".NET 服务目录",
      "keywords": [
        "backend",
        "dotnet",
        "md",
        "net",
        "readme",
        "services",
        "服务目录",
        "一组织各",
        "业务能力",
        "于按业务",
        "务能力划",
        "各服务的",
        "后端服务",
        "并统一组",
        "录用于按",
        "按业务能",
        "服务模块",
        "本目录用",
        "用于按业",
        "目录用于"
      ],
      "relations": {
        "capabilities": [
          "backend",
          "dotnet",
          "services"
        ],
        "framework": null,
        "kind": "readme",
        "language": "dotnet",
        "service": null
      },
      "source_path": "backend/dotnet/Services/README.md",
      "start_line": 1,
      "summary": ".NET 服务目录 in backend/dotnet/Services/README.md"
    },
    {
      "chunk_id": "backend.dotnet.Services.System.README#chunk-001",
      "end_line": 3,
      "heading": "系统服务目录",
      "keywords": [
        "backend",
        "dotnet",
        "md",
        "readme",
        "services",
        "system",
        "系统服务目录",
        "于承载系",
        "典和系统",
        "台字典和",
        "和系统测",
        "基础配置",
        "字典和系",
        "平台字典",
        "录用于承",
        "承载系统",
        "服务目录",
        "本目录用",
        "测试相关",
        "用于承载"
      ],
      "relations": {
        "capabilities": [
          "backend",
          "dotnet",
          "services",
          "system"
        ],
        "framework": null,
        "kind": "readme",
        "language": "dotnet",
        "service": "system"
      },
      "source_path": "backend/dotnet/Services/System/README.md",
      "start_line": 1,
      "summary": "系统服务目录 in backend/dotnet/Services/System/README.md"
    },
    {
      "chunk_id": "backend.java.README#chunk-001",
      "end_line": 3,
      "heading": "Java 后端目录",
      "keywords": [
        "backend",
        "java",
        "md",
        "readme",
        "后端目录",
        "下的后端",
        "件或集成",
        "后端服务",
        "录用于承",
        "成能力实",
        "或集成能",
        "技术栈下",
        "本目录用",
        "术栈下的",
        "栈下的后",
        "用于承载",
        "的后端服",
        "目录用于",
        "组件或集",
        "能力实现"
      ],
      "relations": {
        "capabilities": [
          "backend",
          "java"
        ],
        "framework": null,
        "kind": "readme",
        "language": "java",
        "service": null
      },
      "source_path": "backend/java/README.md",
      "start_line": 1,
      "summary": "Java 后端目录 in backend/java/README.md"
    },
    {
      "chunk_id": "backend.python.README#chunk-001",
      "end_line": 3,
      "heading": "Python 后端目录",
      "keywords": [
        "backend",
        "md",
        "python",
        "readme",
        "后端目录",
        "下的后端",
        "后端服务",
        "实验性能",
        "录用于承",
        "性能力实",
        "或实验性",
        "技术栈下",
        "本或实验",
        "本目录用",
        "术栈下的",
        "栈下的后",
        "用于承载",
        "的后端服",
        "目录用于",
        "能力实现"
      ],
      "relations": {
        "capabilities": [
          "backend",
          "python"
        ],
        "framework": null,
        "kind": "readme",
        "language": "python",
        "service": null
      },
      "source_path": "backend/python/README.md",
      "start_line": 1,
      "summary": "Python 后端目录 in backend/python/README.md"
    },
    {
      "chunk_id": "contracts.README#chunk-001",
      "end_line": 3,
      "heading": "契约目录",
      "keywords": [
        "contracts",
        "md",
        "readme",
        "契约目录",
        "中存放跨",
        "于集中存",
        "作所需的",
        "协作所需",
        "口契约与",
        "契约与数",
        "存放跨服",
        "录用于集",
        "所需的接",
        "接口契约",
        "放跨服务",
        "本目录用",
        "用于集中",
        "的接口契",
        "目录用于",
        "端协作所"
      ],
      "relations": {
        "capabilities": [
          "contracts"
        ],
        "framework": null,
        "kind": "readme",
        "language": "contracts",
        "service": null
      },
      "source_path": "contracts/README.md",
      "start_line": 1,
      "summary": "契约目录 in contracts/README.md"
    },
    {
      "chunk_id": "contracts.openapi.README#chunk-001",
      "end_line": 3,
      "heading": "OpenAPI 契约目录",
      "keywords": [
        "contracts",
        "md",
        "openapi",
        "readme",
        "契约目录",
        "api",
        "http",
        "open",
        "于存放基",
        "口协作说",
        "和接口协",
        "响应模型",
        "型和接口",
        "存放基于",
        "应模型和",
        "录用于存",
        "接口协作",
        "接口规范",
        "本目录用",
        "模型和接"
      ],
      "relations": {
        "capabilities": [
          "contracts",
          "openapi"
        ],
        "framework": null,
        "kind": "readme",
        "language": "contracts",
        "service": null
      },
      "source_path": "contracts/openapi/README.md",
      "start_line": 1,
      "summary": "OpenAPI 契约目录 in contracts/openapi/README.md"
    },
    {
      "chunk_id": "contracts.protos.README#chunk-001",
      "end_line": 3,
      "heading": "Protobuf 契约目录",
      "keywords": [
        "contracts",
        "md",
        "protobuf",
        "protos",
        "readme",
        "契约目录",
        "于存放基",
        "代码来源",
        "务通信协",
        "和生成代",
        "存放基于",
        "录用于存",
        "息结构和",
        "成代码来",
        "服务通信",
        "本目录用",
        "构和生成",
        "消息结构",
        "生成代码",
        "用于存放"
      ],
      "relations": {
        "capabilities": [
          "contracts",
          "protos"
        ],
        "framework": null,
        "kind": "readme",
        "language": "contracts",
        "service": null
      },
      "source_path": "contracts/protos/README.md",
      "start_line": 1,
      "summary": "Protobuf 契约目录 in contracts/protos/README.md"
    },
    {
      "chunk_id": "deploy.README#chunk-001",
      "end_line": 3,
      "heading": "部署目录",
      "keywords": [
        "deploy",
        "md",
        "readme",
        "部署目录",
        "中存放项",
        "于集中存",
        "交付相关",
        "发布和持",
        "和持续交",
        "存放项目",
        "容器编排",
        "布和持续",
        "录用于集",
        "持续交付",
        "放项目部",
        "本目录用",
        "用于集中",
        "目录用于",
        "续交付相",
        "群发布和"
      ],
      "relations": {
        "capabilities": [
          "deploy"
        ],
        "framework": null,
        "kind": "readme",
        "language": "deploy",
        "service": null
      },
      "source_path": "deploy/README.md",
      "start_line": 1,
      "summary": "部署目录 in deploy/README.md"
    },
    {
      "chunk_id": "deploy.ci-cd.README#chunk-001",
      "end_line": 4,
      "heading": "持续交付目录",
      "keywords": [
        "cd",
        "ci",
        "deploy",
        "md",
        "readme",
        "持续交付目录",
        "于存放持",
        "交付目录",
        "动化发布",
        "化发布相",
        "和自动化",
        "存放持续",
        "录用于存",
        "持续交付",
        "持续集成",
        "放持续集",
        "本目录用",
        "水线配置",
        "流水线配",
        "用于存放"
      ],
      "relations": {
        "capabilities": [
          "deploy"
        ],
        "framework": null,
        "kind": "readme",
        "language": "deploy",
        "service": null
      },
      "source_path": "deploy/ci-cd/README.md",
      "start_line": 1,
      "summary": "持续交付目录 in deploy/ci-cd/README.md"
    },
    {
      "chunk_id": "deploy.ci-cd.README#chunk-002",
      "end_line": 14,
      "heading": "TW Memory Check",
      "keywords": [
        "cd",
        "check",
        "ci",
        "deploy",
        "md",
        "memory",
        "readme",
        "chunk",
        "command",
        "freshness",
        "hashes",
        "line",
        "paths",
        "powershell",
        "ps1",
        "ranges",
        "repository",
        "root",
        "route",
        "run"
      ],
      "relations": {
        "capabilities": [
          "deploy"
        ],
        "framework": null,
        "kind": "readme",
        "language": "deploy",
        "service": null
      },
      "source_path": "deploy/ci-cd/README.md",
      "start_line": 5,
      "summary": "TW Memory Check in deploy/ci-cd/README.md"
    },
    {
      "chunk_id": "deploy.docker-compose.README#chunk-001",
      "end_line": 3,
      "heading": "Docker Compose 部署目录",
      "keywords": [
        "compose",
        "deploy",
        "docker",
        "md",
        "readme",
        "部署目录",
        "于存放本",
        "地或轻量",
        "境使用的",
        "存放本地",
        "录用于存",
        "或轻量环",
        "排文件和",
        "放本地或",
        "文件和容",
        "本地或轻",
        "本目录用",
        "环境使用",
        "用于存放",
        "目录用于"
      ],
      "relations": {
        "capabilities": [
          "compose",
          "deploy",
          "docker"
        ],
        "framework": null,
        "kind": "readme",
        "language": "deploy",
        "service": null
      },
      "source_path": "deploy/docker-compose/README.md",
      "start_line": 1,
      "summary": "Docker Compose 部署目录 in deploy/docker-compose/README.md"
    },
    {
      "chunk_id": "deploy.k8s-helm.README#chunk-001",
      "end_line": 3,
      "heading": "Kubernetes 与 Helm 部署目录",
      "keywords": [
        "deploy",
        "helm",
        "k8s",
        "kubernetes",
        "md",
        "readme",
        "部署目录",
        "chart",
        "于存放面",
        "发布配置",
        "和集群发",
        "存放面向",
        "录用于存",
        "本目录用",
        "板和集群",
        "模板和集",
        "环境的",
        "用于存放",
        "目录用于",
        "署模板和"
      ],
      "relations": {
        "capabilities": [
          "deploy",
          "helm",
          "k8s"
        ],
        "framework": null,
        "kind": "readme",
        "language": "deploy",
        "service": null
      },
      "source_path": "deploy/k8s-helm/README.md",
      "start_line": 1,
      "summary": "Kubernetes 与 Helm 部署目录 in deploy/k8s-helm/README.md"
    },
    {
      "chunk_id": "docs.README#chunk-001",
      "end_line": 4,
      "heading": "文档目录",
      "keywords": [
        "docs",
        "md",
        "readme",
        "文档目录",
        "中存放项",
        "于集中存",
        "作规范等",
        "协作规范",
        "和协作规",
        "存放项目",
        "工程标准",
        "录用于集",
        "录结构和",
        "放项目架",
        "本目录用",
        "构和协作",
        "用于集中",
        "目录用于",
        "目录结构",
        "结构和协"
      ],
      "relations": {
        "capabilities": [
          "docs"
        ],
        "framework": null,
        "kind": "readme",
        "language": "docs",
        "service": null
      },
      "source_path": "docs/README.md",
      "start_line": 1,
      "summary": "文档目录 in docs/README.md"
    },
    {
      "chunk_id": "docs.README#chunk-002",
      "end_line": 9,
      "heading": "索引",
      "keywords": [
        "docs",
        "md",
        "readme",
        "standards",
        "superpowers",
        "公司正式",
        "决策和参",
        "包含规则",
        "协作流程",
        "参考资料",
        "司正式规",
        "和参考资",
        "工程规范",
        "式规范资",
        "正式规范",
        "流程",
        "策和参考",
        "索引",
        "规范资产",
        "计与计划"
      ],
      "relations": {
        "capabilities": [
          "docs"
        ],
        "framework": null,
        "kind": "readme",
        "language": "docs",
        "service": null
      },
      "source_path": "docs/README.md",
      "start_line": 5,
      "summary": "索引 in docs/README.md"
    },
    {
      "chunk_id": "docs.README#chunk-003",
      "end_line": 12,
      "heading": "维护约定",
      "keywords": [
        "docs",
        "md",
        "readme",
        "维护约定",
        "brief",
        "check",
        "format",
        "generate",
        "markdown",
        "memory",
        "python",
        "standards",
        "tools",
        "公司治理",
        "司治理资",
        "和公司治",
        "文和公司",
        "正文和公",
        "治理资料",
        "理资料统"
      ],
      "relations": {
        "capabilities": [
          "docs"
        ],
        "framework": null,
        "kind": "readme",
        "language": "docs",
        "service": null
      },
      "source_path": "docs/README.md",
      "start_line": 10,
      "summary": "维护约定 in docs/README.md"
    },
    {
      "chunk_id": "docs.standards.README#chunk-001",
      "end_line": 4,
      "heading": "工程规范目录",
      "keywords": [
        "docs",
        "md",
        "readme",
        "standards",
        "工程规范目录",
        "业务无关",
        "于存放业",
        "务无关的",
        "存放业务",
        "工程规范",
        "录是项目",
        "放业务无",
        "是项目工",
        "本目录是",
        "用于存放",
        "的统一入",
        "目工程规",
        "目录是项",
        "程规范的",
        "程规范目"
      ],
      "relations": {
        "capabilities": [
          "docs",
          "standards"
        ],
        "framework": null,
        "kind": "readme",
        "language": "docs",
        "service": null
      },
      "source_path": "docs/standards/README.md",
      "start_line": 1,
      "summary": "工程规范目录 in docs/standards/README.md"
    },
    {
      "chunk_id": "docs.standards.README#chunk-002",
      "end_line": 8,
      "heading": "使用方式",
      "keywords": [
        "docs",
        "md",
        "readme",
        "standards",
        "使用方式",
        "authoring",
        "markdown",
        "processes",
        "standard",
        "修改规范",
        "可直接阅",
        "增或修改",
        "应是可直",
        "或修改规",
        "接阅读的",
        "改规范时",
        "新增或修",
        "是可直接",
        "正文",
        "每篇规范"
      ],
      "relations": {
        "capabilities": [
          "docs",
          "standards"
        ],
        "framework": null,
        "kind": "readme",
        "language": "docs",
        "service": null
      },
      "source_path": "docs/standards/README.md",
      "start_line": 5,
      "summary": "使用方式 in docs/standards/README.md"
    },
    {
      "chunk_id": "docs.standards.README#chunk-003",
      "end_line": 15,
      "heading": "当前规范",
      "keywords": [
        "docs",
        "md",
        "readme",
        "standards",
        "当前规范",
        "decisions",
        "processes",
        "references",
        "rules",
        "决策记录",
        "参考资料",
        "流程",
        "规则正文"
      ],
      "relations": {
        "capabilities": [
          "docs",
          "standards"
        ],
        "framework": null,
        "kind": "readme",
        "language": "docs",
        "service": null
      },
      "source_path": "docs/standards/README.md",
      "start_line": 9,
      "summary": "当前规范 in docs/standards/README.md"
    },
    {
      "chunk_id": "docs.standards.README#chunk-004",
      "end_line": 26,
      "heading": "同步检查",
      "keywords": [
        "docs",
        "md",
        "readme",
        "standards",
        "同步检查",
        "brief",
        "check",
        "format",
        "generate",
        "memory",
        "powershell",
        "python",
        "tools",
        "从仓库根",
        "仓库根目",
        "修改本目",
        "前仓库没",
        "库根目录",
        "应从仓库",
        "当前仓库"
      ],
      "relations": {
        "capabilities": [
          "docs",
          "standards"
        ],
        "framework": null,
        "kind": "readme",
        "language": "docs",
        "service": null
      },
      "source_path": "docs/standards/README.md",
      "start_line": 16,
      "summary": "同步检查 in docs/standards/README.md"
    },
    {
      "chunk_id": "docs.standards.README#chunk-005",
      "end_line": 30,
      "heading": "治理入口",
      "keywords": [
        "docs",
        "md",
        "readme",
        "standards",
        "治理入口",
        "decisions",
        "flow",
        "processes",
        "rfc",
        "决策记录",
        "流程"
      ],
      "relations": {
        "capabilities": [
          "docs",
          "standards"
        ],
        "framework": null,
        "kind": "readme",
        "language": "docs",
        "service": null
      },
      "source_path": "docs/standards/README.md",
      "start_line": 27,
      "summary": "治理入口 in docs/standards/README.md"
    },
    {
      "chunk_id": "frontend.README#chunk-001",
      "end_line": 3,
      "heading": "前端目录",
      "keywords": [
        "frontend",
        "md",
        "readme",
        "前端目录",
        "中存放前",
        "于集中存",
        "享前端包",
        "共享前端",
        "前端应用",
        "和共享前",
        "存放前端",
        "并承载多",
        "应用和共",
        "录用于集",
        "承载多端",
        "放前端应",
        "本目录用",
        "用于集中",
        "用和共享",
        "目录用于"
      ],
      "relations": {
        "capabilities": [
          "frontend"
        ],
        "framework": null,
        "kind": "readme",
        "language": "frontend",
        "service": null
      },
      "source_path": "frontend/README.md",
      "start_line": 1,
      "summary": "前端目录 in frontend/README.md"
    },
    {
      "chunk_id": "frontend.apps.README#chunk-001",
      "end_line": 3,
      "heading": "前端应用目录",
      "keywords": [
        "apps",
        "frontend",
        "md",
        "readme",
        "前端应用目录",
        "不同业务",
        "业务角色",
        "中存放面",
        "于集中存",
        "前端应用",
        "务角色和",
        "同业务角",
        "向不同业",
        "存放面向",
        "应用目录",
        "录用于集",
        "放面向不",
        "本目录用",
        "用于集中",
        "目录用于"
      ],
      "relations": {
        "capabilities": [
          "apps",
          "frontend"
        ],
        "framework": null,
        "kind": "readme",
        "language": "frontend",
        "service": null
      },
      "source_path": "frontend/apps/README.md",
      "start_line": 1,
      "summary": "前端应用目录 in frontend/apps/README.md"
    },
    {
      "chunk_id": "frontend.apps.tw.app.owner.README#chunk-001",
      "end_line": 3,
      "heading": "业主端应用目录",
      "keywords": [
        "app",
        "apps",
        "frontend",
        "md",
        "owner",
        "readme",
        "tw",
        "业主端应用目录",
        "业主使用",
        "业主端应",
        "主使用场",
        "主端应用",
        "于承载面",
        "使用场景",
        "向业主使",
        "场景的前",
        "应用目录",
        "录用于承",
        "承载面向",
        "景的前端"
      ],
      "relations": {
        "capabilities": [
          "app",
          "apps",
          "frontend",
          "owner"
        ],
        "framework": null,
        "kind": "readme",
        "language": "frontend",
        "service": "tw.app.owner"
      },
      "source_path": "frontend/apps/tw.app.owner/README.md",
      "start_line": 1,
      "summary": "业主端应用目录 in frontend/apps/tw.app.owner/README.md"
    },
    {
      "chunk_id": "frontend.apps.tw.app.staff.README#chunk-001",
      "end_line": 3,
      "heading": "员工端应用目录",
      "keywords": [
        "app",
        "apps",
        "frontend",
        "md",
        "readme",
        "staff",
        "tw",
        "员工端应用目录",
        "于承载面",
        "使用场景",
        "向员工使",
        "员工使用",
        "员工端应",
        "场景的前",
        "工使用场",
        "工端应用",
        "应用目录",
        "录用于承",
        "承载面向",
        "景的前端"
      ],
      "relations": {
        "capabilities": [
          "app",
          "apps",
          "frontend",
          "staff"
        ],
        "framework": null,
        "kind": "readme",
        "language": "frontend",
        "service": "tw.app.staff"
      },
      "source_path": "frontend/apps/tw.app.staff/README.md",
      "start_line": 1,
      "summary": "员工端应用目录 in frontend/apps/tw.app.staff/README.md"
    },
    {
      "chunk_id": "frontend.apps.tw.web.client.README#chunk-001",
      "end_line": 3,
      "heading": "客户端 Web 应用目录",
      "keywords": [
        "apps",
        "client",
        "frontend",
        "md",
        "readme",
        "tw",
        "web",
        "客户端",
        "应用目录",
        "于承载面",
        "使用场景",
        "前端应用",
        "向客户使",
        "客户使用",
        "应用代码",
        "录用于承",
        "户使用场",
        "承载面向",
        "本目录用",
        "用于承载"
      ],
      "relations": {
        "capabilities": [
          "apps",
          "client",
          "frontend",
          "web"
        ],
        "framework": null,
        "kind": "readme",
        "language": "frontend",
        "service": "tw.web.client"
      },
      "source_path": "frontend/apps/tw.web.client/README.md",
      "start_line": 1,
      "summary": "客户端 Web 应用目录 in frontend/apps/tw.web.client/README.md"
    },
    {
      "chunk_id": "frontend.apps.tw.web.ops.README#chunk-001",
      "end_line": 3,
      "heading": "运营 Web 应用目录",
      "keywords": [
        "apps",
        "frontend",
        "md",
        "ops",
        "readme",
        "tw",
        "web",
        "应用目录",
        "于承载面",
        "前端应用",
        "向运营管",
        "应用代码",
        "录用于承",
        "承载面向",
        "本目录用",
        "理场景的",
        "用于承载",
        "用代码与",
        "目录用于",
        "端应用代"
      ],
      "relations": {
        "capabilities": [
          "apps",
          "frontend",
          "ops",
          "web"
        ],
        "framework": null,
        "kind": "readme",
        "language": "frontend",
        "service": "tw.web.ops"
      },
      "source_path": "frontend/apps/tw.web.ops/README.md",
      "start_line": 1,
      "summary": "运营 Web 应用目录 in frontend/apps/tw.web.ops/README.md"
    },
    {
      "chunk_id": "frontend.apps.tw.web.portal.README#chunk-001",
      "end_line": 3,
      "heading": "门户 Web 应用目录",
      "keywords": [
        "apps",
        "frontend",
        "md",
        "portal",
        "readme",
        "tw",
        "web",
        "应用目录",
        "于承载面",
        "代码与页",
        "前端应用",
        "向门户场",
        "应用代码",
        "录用于承",
        "户场景的",
        "承载面向",
        "本目录用",
        "用于承载",
        "用代码与",
        "目录用于"
      ],
      "relations": {
        "capabilities": [
          "apps",
          "frontend",
          "portal",
          "web"
        ],
        "framework": null,
        "kind": "readme",
        "language": "frontend",
        "service": "tw.web.portal"
      },
      "source_path": "frontend/apps/tw.web.portal/README.md",
      "start_line": 1,
      "summary": "门户 Web 应用目录 in frontend/apps/tw.web.portal/README.md"
    },
    {
      "chunk_id": "frontend.packages.README#chunk-001",
      "end_line": 3,
      "heading": "前端共享包目录",
      "keywords": [
        "frontend",
        "md",
        "packages",
        "readme",
        "前端共享包目录",
        "个前端应",
        "于存放可",
        "享包目录",
        "共享包目",
        "前端共享",
        "前端应用",
        "可被多个",
        "复用的组",
        "多个前端",
        "存放可被",
        "应用复用",
        "录用于存",
        "放可被多",
        "本目录用",
        "用于存放"
      ],
      "relations": {
        "capabilities": [
          "frontend",
          "packages"
        ],
        "framework": null,
        "kind": "readme",
        "language": "frontend",
        "service": null
      },
      "source_path": "frontend/packages/README.md",
      "start_line": 1,
      "summary": "前端共享包目录 in frontend/packages/README.md"
    }
  ],
  "schema_version": "1.0.0"
}
